{
  "$schema": "https://ui.shadcn.com/schema/registry-item.json",
  "name": "icons-plugins-dart-observatory",
  "type": "registry:ui",
  "title": "Observatory",
  "description": "Observatory icon from Plugins Dart category.",
  "registryDependencies": [
    "icons-plugins-types",
    "icons-components"
  ],
  "files": [
    {
      "path": "registry/icons/plugins/dart/index.ts",
      "type": "registry:ui",
      "target": "components/jetbrains-ui/icons/plugins/dart/index.ts"
    },
    {
      "path": "public/icons/plugins.svg",
      "type": "registry:ui",
      "target": "public/icons/plugins.svg"
    }
  ],
  "meta": {
    "keywords": [
      "observatory",
      "icon",
      "plugins",
      "dart",
      "jetbrains"
    ]
  }
}
