{
  "$schema": "https://ui.shadcn.com/schema/registry-item.json",
  "name": "icons-general-windows-minimize",
  "type": "registry:ui",
  "title": "Minimize",
  "description": "Minimize icon from General Windows category.",
  "registryDependencies": [
    "icons-general-types"
  ],
  "files": [
    {
      "path": "registry/icons/general/windows/minimize/index.tsx",
      "type": "registry:ui",
      "target": "components/jetbrains-ui/icons/general/windows/minimize/index.tsx"
    }
  ],
  "meta": {
    "keywords": [
      "minimize",
      "icon",
      "general",
      "windows",
      "jetbrains"
    ]
  }
}
