{
  "$schema": "https://ui.shadcn.com/schema/registry-item.json",
  "name": "icons-plugins-cidr-code-assistant-parameter",
  "type": "registry:ui",
  "title": "Code Assistant Parameter",
  "description": "Code Assistant Parameter icon from Plugins Cidr category.",
  "registryDependencies": [
    "icons-plugins-types"
  ],
  "files": [
    {
      "path": "registry/icons/plugins/cidr/code-assistant-parameter/index.tsx",
      "type": "registry:ui",
      "target": "components/jetbrains-ui/icons/plugins/cidr/code-assistant-parameter/index.tsx"
    }
  ],
  "meta": {
    "keywords": [
      "code-assistant-parameter",
      "icon",
      "plugins",
      "cidr",
      "jetbrains"
    ]
  }
}
