{
  "$schema": "https://ui.shadcn.com/schema/registry-item.json",
  "name": "icons-debugger-thread-frozen",
  "type": "registry:ui",
  "title": "Thread Frozen",
  "description": "Thread Frozen icon from Debugger category.",
  "registryDependencies": [
    "icons-debugger-types"
  ],
  "files": [
    {
      "path": "registry/icons/debugger/thread-frozen/index.tsx",
      "type": "registry:ui",
      "target": "components/jetbrains-ui/icons/debugger/thread-frozen/index.tsx"
    }
  ],
  "meta": {
    "keywords": [
      "thread-frozen",
      "icon",
      "debugger",
      "jetbrains"
    ]
  }
}
