{
  "$schema": "https://ui.shadcn.com/schema/registry-item.json",
  "name": "icons-database-single-record-view",
  "type": "registry:ui",
  "title": "Single Record View",
  "description": "Single Record View icon from Database category.",
  "registryDependencies": [
    "icons-database-types",
    "icons-components"
  ],
  "files": [
    {
      "path": "registry/icons/database/index.ts",
      "type": "registry:ui",
      "target": "components/jetbrains-ui/icons/database/index.ts"
    },
    {
      "path": "public/icons/database.svg",
      "type": "registry:ui",
      "target": "public/icons/database.svg"
    }
  ],
  "meta": {
    "keywords": [
      "single-record-view",
      "icon",
      "database",
      "jetbrains"
    ]
  }
}
