{
  "$schema": "https://ui.shadcn.com/schema/registry-item.json",
  "name": "icons-general-tool-windows-statistics-event-log",
  "type": "registry:ui",
  "title": "Statistics Event Log",
  "description": "Statistics Event Log icon from General Tool Windows category.",
  "registryDependencies": [
    "icons-general-types"
  ],
  "files": [
    {
      "path": "registry/icons/general/tool-windows/statistics-event-log/index.tsx",
      "type": "registry:ui",
      "target": "components/jetbrains-ui/icons/general/tool-windows/statistics-event-log/index.tsx"
    }
  ],
  "meta": {
    "keywords": [
      "statistics-event-log",
      "icon",
      "general",
      "tool-windows",
      "jetbrains"
    ]
  }
}
