{
  "$schema": "https://ui.shadcn.com/schema/registry-item.json",
  "name": "icons-file-types-pnpm-lock",
  "type": "registry:ui",
  "title": "Pnpm Lock",
  "description": "Pnpm Lock icon from File Types category.",
  "registryDependencies": [
    "icons-file-types-types",
    "icons-components"
  ],
  "files": [
    {
      "path": "registry/icons/file-types/index.ts",
      "type": "registry:ui",
      "target": "components/jetbrains-ui/icons/file-types/index.ts"
    },
    {
      "path": "public/icons/file-types.svg",
      "type": "registry:ui",
      "target": "public/icons/file-types.svg"
    }
  ],
  "meta": {
    "keywords": [
      "pnpm-lock",
      "icon",
      "file-types",
      "jetbrains"
    ]
  }
}
