{
  "$schema": "https://ui.shadcn.com/schema/registry-item.json",
  "name": "icons-database-azure",
  "type": "registry:ui",
  "title": "Azure",
  "description": "Azure icon from Database category.",
  "registryDependencies": [
    "icons-database-types"
  ],
  "files": [
    {
      "path": "registry/icons/database/azure/index.tsx",
      "type": "registry:ui",
      "target": "components/jetbrains-ui/icons/database/azure/index.tsx"
    }
  ],
  "meta": {
    "keywords": [
      "azure",
      "icon",
      "database",
      "jetbrains"
    ]
  }
}
