{
  "$schema": "https://ui.shadcn.com/schema/registry-item.json",
  "name": "icons-plugins-ruby-rake-task-def-node",
  "type": "registry:ui",
  "title": "Rake Task Def Node",
  "description": "Rake Task Def Node icon from Plugins Ruby category.",
  "registryDependencies": [
    "icons-plugins-types",
    "icons-components"
  ],
  "files": [
    {
      "path": "registry/icons/plugins/ruby/index.ts",
      "type": "registry:ui",
      "target": "components/jetbrains-ui/icons/plugins/ruby/index.ts"
    },
    {
      "path": "public/icons/plugins.svg",
      "type": "registry:ui",
      "target": "public/icons/plugins.svg"
    }
  ],
  "meta": {
    "keywords": [
      "rake-task-def-node",
      "icon",
      "plugins",
      "ruby",
      "jetbrains"
    ]
  }
}
