{
  "name": "icons-plugins-cidr-code-assistant-property-optional",
  "type": "registry:ui",
  "title": "Code Assistant Property Optional",
  "description": "Code Assistant Property Optional icon from Plugins Cidr category.",
  "registryDependencies": [
    "utils",
    "@jetbrains-ui/icons-plugins-types"
  ],
  "files": [
    {
      "path": "registry/icons/plugins/cidr/code-assistant-property-optional/index.tsx",
      "type": "registry:ui",
      "target": "components/jetbrains-ui/icons/plugins/cidr/code-assistant-property-optional/index.tsx",
      "content": "import React from 'react';\nimport { cn } from '@/lib/utils';\nimport { type IconProps, type SvgProps, sizeMap } from '../../types';\n\nexport type CodeAssistantPropertyOptionalProps = IconProps;\n\nconst CodeAssistantPropertyOptionalLight: React.FC<SvgProps> = ({\n  size,\n  className,\n  title,\n  role,\n  'aria-label': ariaLabel,\n  'aria-hidden': ariaHidden,\n}) => (\n  <svg\n    width={size}\n    height={size}\n    viewBox=\"0 0 16 16\"\n    fill=\"none\"\n    xmlns=\"http://www.w3.org/2000/svg\"\n    className={className}\n    role={role}\n    aria-label={ariaLabel}\n    aria-hidden={ariaHidden}\n  >\n    {title && <title>{title}</title>}\n    <rect\n      x=\"2.5\"\n      y=\"2.5\"\n      width=\"11\"\n      height=\"11\"\n      rx=\"5.5\"\n      fill=\"#FFF7F7\"\n      stroke=\"#DB3B4B\"\n    />\n    <path\n      d=\"M6 4.98h2.52q.61 0 1.07.223.465.223.714.634.255.412.254.952 0 .544-.258.955-.255.412-.722.639a2.5 2.5 0 0 1-1.093.227H6.98v2.37H6zm2.477 2.786q.318 0 .559-.116a.87.87 0 0 0 .37-.339q.129-.222.129-.518a1 1 0 0 0-.13-.514.84.84 0 0 0-.37-.335q-.24-.12-.558-.12H6.98v1.942z\"\n      fill=\"#DB3B4B\"\n    />\n  </svg>\n);\n\nconst CodeAssistantPropertyOptionalDark: React.FC<SvgProps> = ({\n  size,\n  className,\n  title,\n  role,\n  'aria-label': ariaLabel,\n  'aria-hidden': ariaHidden,\n}) => (\n  <svg\n    width={size}\n    height={size}\n    viewBox=\"0 0 16 16\"\n    fill=\"none\"\n    xmlns=\"http://www.w3.org/2000/svg\"\n    className={className}\n    role={role}\n    aria-label={ariaLabel}\n    aria-hidden={ariaHidden}\n  >\n    {title && <title>{title}</title>}\n    <rect\n      x=\"2.5\"\n      y=\"2.5\"\n      width=\"11\"\n      height=\"11\"\n      rx=\"5.5\"\n      fill=\"#402929\"\n      stroke=\"#DB5C5C\"\n    />\n    <path\n      d=\"M6 4.98h2.52q.61 0 1.07.223.465.223.714.634.255.412.254.952 0 .544-.258.955-.255.412-.722.639a2.5 2.5 0 0 1-1.093.227H6.98v2.37H6zm2.477 2.786q.318 0 .559-.116a.87.87 0 0 0 .37-.339q.129-.222.129-.518a1 1 0 0 0-.13-.514.84.84 0 0 0-.37-.335q-.24-.12-.558-.12H6.98v1.942z\"\n      fill=\"#DB5C5C\"\n    />\n  </svg>\n);\n\nexport const CodeAssistantPropertyOptional: React.FC<\n  CodeAssistantPropertyOptionalProps\n> = ({\n  size = 'md',\n  mode = 'light',\n  className,\n  'aria-label': ariaLabel,\n  title,\n  ...props\n}) => {\n  const SvgComponent =\n    mode === 'light'\n      ? CodeAssistantPropertyOptionalLight\n      : CodeAssistantPropertyOptionalDark;\n\n  return (\n    <SvgComponent\n      size={sizeMap[size]}\n      className={cn('inline-block flex-shrink-0', className)}\n      title={title}\n      role={ariaLabel ? 'img' : 'presentation'}\n      aria-label={ariaLabel}\n      aria-hidden={!ariaLabel}\n      {...props}\n    />\n  );\n};"
    }
  ],
  "meta": {
    "keywords": [
      "code-assistant-property-optional",
      "icon",
      "plugins",
      "cidr",
      "jetbrains"
    ]
  }
}