{
  "name": "icons-plugins-platformio-clean",
  "type": "registry:ui",
  "title": "Clean",
  "description": "Clean icon from Plugins Platformio category.",
  "registryDependencies": [
    "utils",
    "@jetbrains-ui/icons-plugins-types"
  ],
  "files": [
    {
      "path": "registry/icons/plugins/platformio/clean/index.tsx",
      "type": "registry:ui",
      "target": "components/jetbrains-ui/icons/plugins/platformio/clean/index.tsx",
      "content": "import React from 'react';\nimport { cn } from '@/lib/utils';\nimport { type IconProps, type SvgProps, sizeMap } from '../../types';\n\nexport type CleanProps = IconProps;\n\nconst CleanLight: React.FC<SvgProps> = ({\n  size,\n  className,\n  title,\n  role,\n  'aria-label': ariaLabel,\n  'aria-hidden': ariaHidden,\n}) => (\n  <svg\n    width={size}\n    height={size}\n    viewBox=\"0 0 16 16\"\n    fill=\"none\"\n    xmlns=\"http://www.w3.org/2000/svg\"\n    className={className}\n    role={role}\n    aria-label={ariaLabel}\n    aria-hidden={ariaHidden}\n  >\n    {title && <title>{title}</title>}\n    <g clipPath=\"url(#a)\">\n      <path\n        d=\"M8.936 10.143 7.63 14.488a6.5 6.5 0 0 1-6.12-6.12l4.345-1.305z\"\n        stroke=\"#6C707E\"\n      />\n      <path d=\"M14.5 1.5 10 6\" stroke=\"#6C707E\" strokeLinecap=\"round\" />\n      <path\n        d=\"m6.86 6.357.105-.105a1.972 1.972 0 0 1 2.789 2.789l-.106.105\"\n        stroke=\"#6C707E\"\n      />\n      <g clipPath=\"url(#b)\">\n        <path\n          d=\"M13 16v-5.647q.554.003 1.09.135l.208-.72a.4.4 0 0 1-.205-.35.422.422 0 0 1 .845 0 .413.413 0 0 1-.385.407l-.21.733c.8.253 1.66.815 1.66 2.067C15.997 14.372 13.557 16 13 16\"\n          fill=\"#E66D17\"\n        />\n        <path\n          d=\"M13.752 14.15c-.475-.734-.275-2.444.968-2.688a.81.81 0 0 1 .881.645c.31 1.02-1.516 2.447-1.849 2.044\"\n          fill=\"#fff\"\n        />\n        <path\n          d=\"M14.5 12.577a.37.37 0 0 0-.35.453.373.373 0 0 0 .736-.08.38.38 0 0 0-.385-.373M11.903 10.505l-.206-.748a.4.4 0 0 0 .196-.345.422.422 0 0 0-.846 0 .415.415 0 0 0 .421.409l.206.75c-.803.257-1.674.821-1.674 2.054.018 1.781 2.44 3.375 2.997 3.375v-5.647q-.557.012-1.094.152\"\n          fill=\"#E66D17\"\n        />\n        <path\n          d=\"M12.33 14.151c-.333.404-2.16-1.024-1.85-2.044a.81.81 0 0 1 .883-.645c1.243.245 1.444 1.954.968 2.69\"\n          fill=\"#fff\"\n        />\n        <path\n          d=\"M11.56 12.588a.373.373 0 1 0 .384.373.38.38 0 0 0-.385-.373\"\n          fill=\"#E66D17\"\n        />\n      </g>\n    </g>\n    <defs>\n      <clipPath id=\"a\">\n        <path fill=\"#fff\" d=\"M0 0H16V16H0z\" />\n      </clipPath>\n      <clipPath id=\"b\">\n        <path fill=\"#fff\" d=\"M0 0H16V16H0z\" />\n      </clipPath>\n    </defs>\n  </svg>\n);\n\nconst CleanDark: React.FC<SvgProps> = ({\n  size,\n  className,\n  title,\n  role,\n  'aria-label': ariaLabel,\n  'aria-hidden': ariaHidden,\n}) => (\n  <svg\n    width={size}\n    height={size}\n    viewBox=\"0 0 16 16\"\n    fill=\"none\"\n    xmlns=\"http://www.w3.org/2000/svg\"\n    className={className}\n    role={role}\n    aria-label={ariaLabel}\n    aria-hidden={ariaHidden}\n  >\n    {title && <title>{title}</title>}\n    <g clipPath=\"url(#a)\">\n      <path\n        d=\"M8.936 10.143 7.63 14.488a6.5 6.5 0 0 1-6.12-6.12l4.345-1.305z\"\n        stroke=\"#CED0D6\"\n      />\n      <path d=\"M14.5 1.5 10 6\" stroke=\"#CED0D6\" strokeLinecap=\"round\" />\n      <path\n        d=\"m6.86 6.357.105-.105a1.972 1.972 0 0 1 2.789 2.789l-.106.105\"\n        stroke=\"#CED0D6\"\n      />\n      <g clipPath=\"url(#b)\">\n        <path\n          d=\"M13 16v-5.647q.554.003 1.09.135l.208-.72a.4.4 0 0 1-.205-.35.422.422 0 0 1 .845 0 .413.413 0 0 1-.385.407l-.21.733c.8.253 1.66.815 1.66 2.067C15.997 14.372 13.557 16 13 16\"\n          fill=\"#C77D55\"\n        />\n        <path\n          d=\"M13.752 14.15c-.475-.734-.275-2.444.968-2.688a.81.81 0 0 1 .881.645c.31 1.02-1.516 2.447-1.849 2.044\"\n          fill=\"#fff\"\n        />\n        <path\n          d=\"M14.5 12.577a.37.37 0 0 0-.35.453.373.373 0 0 0 .736-.08.38.38 0 0 0-.385-.373M11.903 10.505l-.206-.748a.4.4 0 0 0 .196-.345.422.422 0 0 0-.846 0 .415.415 0 0 0 .421.409l.206.75c-.803.257-1.674.821-1.674 2.054.018 1.781 2.44 3.375 2.997 3.375v-5.647q-.557.012-1.094.152\"\n          fill=\"#C77D55\"\n        />\n        <path\n          d=\"M12.33 14.151c-.333.404-2.16-1.024-1.85-2.044a.81.81 0 0 1 .883-.645c1.243.245 1.444 1.954.968 2.69\"\n          fill=\"#fff\"\n        />\n        <path\n          d=\"M11.56 12.588a.373.373 0 1 0 .384.373.38.38 0 0 0-.385-.373\"\n          fill=\"#C77D55\"\n        />\n      </g>\n    </g>\n    <defs>\n      <clipPath id=\"a\">\n        <path fill=\"#fff\" d=\"M0 0H16V16H0z\" />\n      </clipPath>\n      <clipPath id=\"b\">\n        <path fill=\"#fff\" d=\"M0 0H16V16H0z\" />\n      </clipPath>\n    </defs>\n  </svg>\n);\n\nexport const Clean: React.FC<CleanProps> = ({\n  size = 'md',\n  mode = 'light',\n  className,\n  'aria-label': ariaLabel,\n  title,\n  ...props\n}) => {\n  const SvgComponent = mode === 'light' ? CleanLight : CleanDark;\n\n  return (\n    <SvgComponent\n      size={sizeMap[size]}\n      className={cn('inline-block flex-shrink-0', className)}\n      title={title}\n      role={ariaLabel ? 'img' : 'presentation'}\n      aria-label={ariaLabel}\n      aria-hidden={!ariaLabel}\n      {...props}\n    />\n  );\n};"
    }
  ],
  "meta": {
    "keywords": [
      "clean",
      "icon",
      "plugins",
      "platformio",
      "jetbrains"
    ]
  }
}