{
  "name": "icons-general-modifiers-process-mark",
  "type": "registry:ui",
  "title": "Process Mark",
  "description": "Process Mark icon from General Modifiers category.",
  "registryDependencies": [
    "utils",
    "@jetbrains-ui/icons-general-types"
  ],
  "files": [
    {
      "path": "registry/icons/general/modifiers/process-mark/index.tsx",
      "type": "registry:ui",
      "target": "components/jetbrains-ui/icons/general/modifiers/process-mark/index.tsx",
      "content": "import type { FC } from 'react';\nimport { cn } from '@/lib/utils';\nimport { type IconProps, type SvgProps, sizeMap } from '../../types';\n\nexport type ProcessMarkProps = IconProps;\n\nconst ProcessMarkLight: FC<SvgProps> = ({\n  size,\n  className,\n  title,\n  role,\n  'aria-label': ariaLabel,\n  'aria-hidden': ariaHidden,\n}) => (\n  <svg\n    width={size}\n    height={size}\n    viewBox=\"0 0 16 16\"\n    fill=\"none\"\n    xmlns=\"http://www.w3.org/2000/svg\"\n    className={className}\n    role={role}\n    aria-label={ariaLabel}\n    aria-hidden={ariaHidden}\n  >\n    {title ? <title>{title}</title> : null}\n    <path d=\"M12.5 16a3.5 3.5 0 1 0 0-7 3.5 3.5 0 0 0 0 7\" fill=\"#4682FA\" />\n    <path\n      fillRule=\"evenodd\"\n      clipRule=\"evenodd\"\n      d=\"M12.146 10.146a.5.5 0 0 1 .708 0l2 2a.5.5 0 0 1 0 .708l-2 2a.5.5 0 0 1-.708-.708L13.293 13H10.5a.5.5 0 0 1 0-1h2.793l-1.147-1.146a.5.5 0 0 1 0-.708\"\n      fill=\"#fff\"\n    />\n  </svg>\n);\n\nconst ProcessMarkDark: FC<SvgProps> = ({\n  size,\n  className,\n  title,\n  role,\n  'aria-label': ariaLabel,\n  'aria-hidden': ariaHidden,\n}) => (\n  <svg\n    width={size}\n    height={size}\n    viewBox=\"0 0 16 16\"\n    fill=\"none\"\n    xmlns=\"http://www.w3.org/2000/svg\"\n    className={className}\n    role={role}\n    aria-label={ariaLabel}\n    aria-hidden={ariaHidden}\n  >\n    {title ? <title>{title}</title> : null}\n    <path d=\"M12.5 16a3.5 3.5 0 1 0 0-7 3.5 3.5 0 0 0 0 7\" fill=\"#548AF7\" />\n    <path\n      fillRule=\"evenodd\"\n      clipRule=\"evenodd\"\n      d=\"M12.146 10.146a.5.5 0 0 1 .708 0l2 2a.5.5 0 0 1 0 .708l-2 2a.5.5 0 0 1-.708-.708L13.293 13H10.5a.5.5 0 0 1 0-1h2.793l-1.147-1.146a.5.5 0 0 1 0-.708\"\n      fill=\"#fff\"\n    />\n  </svg>\n);\n\nexport const ProcessMark: FC<ProcessMarkProps> = ({\n  size = 'md',\n  mode = 'light',\n  className,\n  'aria-label': ariaLabel,\n  title,\n  ...props\n}) => {\n  const SvgComponent = mode === 'light' ? ProcessMarkLight : ProcessMarkDark;\n\n  return (\n    <SvgComponent\n      size={sizeMap[size]}\n      className={cn('inline-block flex-shrink-0', className)}\n      title={title}\n      role={ariaLabel ? 'img' : 'presentation'}\n      aria-label={ariaLabel}\n      aria-hidden={!ariaLabel}\n      {...props}\n    />\n  );\n};"
    }
  ],
  "meta": {
    "keywords": [
      "process-mark",
      "icon",
      "general",
      "modifiers",
      "jetbrains"
    ]
  }
}