{
  "name": "icons-general-tool-windows-endpoints",
  "type": "registry:ui",
  "title": "Endpoints",
  "description": "Endpoints icon from General Tool Windows category.",
  "registryDependencies": [
    "utils",
    "@jetbrains-ui/icons-general-types"
  ],
  "files": [
    {
      "path": "registry/icons/general/tool-windows/endpoints/index.tsx",
      "type": "registry:ui",
      "target": "components/jetbrains-ui/icons/general/tool-windows/endpoints/index.tsx",
      "content": "import type { FC } from 'react';\nimport { cn } from '@/lib/utils';\nimport { type IconProps, type SvgProps, sizeMap } from '../../types';\n\nexport type EndpointsProps = IconProps;\n\nconst EndpointsLight: FC<SvgProps> = ({\n  size,\n  className,\n  title,\n  role,\n  'aria-label': ariaLabel,\n  'aria-hidden': ariaHidden,\n}) => (\n  <svg\n    width={size}\n    height={size}\n    viewBox=\"0 0 16 16\"\n    fill=\"none\"\n    xmlns=\"http://www.w3.org/2000/svg\"\n    className={className}\n    role={role}\n    aria-label={ariaLabel}\n    aria-hidden={ariaHidden}\n  >\n    {title ? <title>{title}</title> : null}\n    <path\n      d=\"M8 2c-1.458 0-2.794.52-3.834 1.384a.5.5 0 0 1-.64-.768 7 7 0 1 1 0 10.769.5.5 0 1 1 .64-.77A6 6 0 1 0 8 2\"\n      fill=\"#6C707E\"\n    />\n    <path\n      fillRule=\"evenodd\"\n      clipRule=\"evenodd\"\n      d=\"M0 8a.5.5 0 0 1 .5-.5h4.541a3 3 0 1 1 0 1H.5A.5.5 0 0 1 0 8m6 0a2 2 0 1 0 4 0 2 2 0 0 0-4 0\"\n      fill=\"#6C707E\"\n    />\n  </svg>\n);\n\nconst EndpointsDark: FC<SvgProps> = ({\n  size,\n  className,\n  title,\n  role,\n  'aria-label': ariaLabel,\n  'aria-hidden': ariaHidden,\n}) => (\n  <svg\n    width={size}\n    height={size}\n    viewBox=\"0 0 16 16\"\n    fill=\"none\"\n    xmlns=\"http://www.w3.org/2000/svg\"\n    className={className}\n    role={role}\n    aria-label={ariaLabel}\n    aria-hidden={ariaHidden}\n  >\n    {title ? <title>{title}</title> : null}\n    <path\n      d=\"M8 2c-1.458 0-2.794.52-3.834 1.384a.5.5 0 0 1-.64-.768 7 7 0 1 1 0 10.769.5.5 0 1 1 .64-.77A6 6 0 1 0 8 2\"\n      fill=\"#CED0D6\"\n    />\n    <path\n      fillRule=\"evenodd\"\n      clipRule=\"evenodd\"\n      d=\"M0 8a.5.5 0 0 1 .5-.5h4.541a3 3 0 1 1 0 1H.5A.5.5 0 0 1 0 8m6 0a2 2 0 1 0 4 0 2 2 0 0 0-4 0\"\n      fill=\"#CED0D6\"\n    />\n  </svg>\n);\n\nexport const Endpoints: FC<EndpointsProps> = ({\n  size = 'md',\n  mode = 'light',\n  className,\n  'aria-label': ariaLabel,\n  title,\n  ...props\n}) => {\n  const SvgComponent = mode === 'light' ? EndpointsLight : EndpointsDark;\n\n  return (\n    <SvgComponent\n      size={sizeMap[size]}\n      className={cn('inline-block flex-shrink-0', className)}\n      title={title}\n      role={ariaLabel ? 'img' : 'presentation'}\n      aria-label={ariaLabel}\n      aria-hidden={!ariaLabel}\n      {...props}\n    />\n  );\n};"
    }
  ],
  "meta": {
    "keywords": [
      "endpoints",
      "icon",
      "general",
      "tool-windows",
      "jetbrains"
    ]
  }
}