{
  "name": "icons-editor-icons-overriding-method",
  "type": "registry:ui",
  "title": "Overriding Method",
  "description": "Overriding Method icon from Editor Icons category.",
  "registryDependencies": [
    "utils",
    "@jetbrains-ui/icons-editor-icons-types"
  ],
  "files": [
    {
      "path": "registry/icons/editor-icons/overriding-method/index.tsx",
      "type": "registry:ui",
      "target": "components/jetbrains-ui/icons/editor-icons/overriding-method/index.tsx",
      "content": "import type { FC } from 'react';\nimport { cn } from '@/lib/utils';\nimport { type IconProps, type SvgProps, sizeMap } from '../types';\n\nexport type OverridingMethodProps = IconProps;\n\nconst OverridingMethodLight: FC<SvgProps> = ({\n  size,\n  className,\n  title,\n  role,\n  'aria-label': ariaLabel,\n  'aria-hidden': ariaHidden,\n}) => (\n  <svg\n    width={size}\n    height={size}\n    viewBox=\"0 0 14 14\"\n    fill=\"none\"\n    xmlns=\"http://www.w3.org/2000/svg\"\n    className={className}\n    role={role}\n    aria-label={ariaLabel}\n    aria-hidden={ariaHidden}\n  >\n    {title ? <title>{title}</title> : null}\n    <path d=\"M10 7a4.5 4.5 0 1 1-9 0 4.5 4.5 0 0 1 9 0\" fill=\"#EDF3FF\" />\n    <path\n      fillRule=\"evenodd\"\n      clipRule=\"evenodd\"\n      d=\"M5.492 10C3.73 10 2.5 8.65 2.5 7.017V7c0-1.633 1.246-3 3.008-3S8.5 5.35 8.5 6.983V7c0 1.633-1.246 3-3.008 3m.016-.945c1.14 0 1.935-.911 1.935-2.038V7c0-1.127-.812-2.055-1.951-2.055s-1.935.911-1.935 2.038V7c0 1.127.812 2.055 1.951 2.055\"\n      fill=\"#3574F0\"\n    />\n    <path\n      fillRule=\"evenodd\"\n      clipRule=\"evenodd\"\n      d=\"M11.5 8a.5.5 0 0 1-.5-.5V1.707L9.854 2.854a.5.5 0 1 1-.708-.708l2-2a.5.5 0 0 1 .708 0l2 2a.5.5 0 0 1-.708.708L12 1.707V7.5a.5.5 0 0 1-.5.5\"\n      fill=\"#DB3B4B\"\n    />\n    <path\n      d=\"M10 7a4.5 4.5 0 1 1-1.578-3.422l.017-.017a1.5 1.5 0 0 1-.391-1.437 5.5 5.5 0 1 0 2.66 6.65A1.5 1.5 0 0 1 10 7.5z\"\n      fill=\"#3574F0\"\n    />\n  </svg>\n);\n\nconst OverridingMethodDark: FC<SvgProps> = ({\n  size,\n  className,\n  title,\n  role,\n  'aria-label': ariaLabel,\n  'aria-hidden': ariaHidden,\n}) => (\n  <svg\n    width={size}\n    height={size}\n    viewBox=\"0 0 14 14\"\n    fill=\"none\"\n    xmlns=\"http://www.w3.org/2000/svg\"\n    className={className}\n    role={role}\n    aria-label={ariaLabel}\n    aria-hidden={ariaHidden}\n  >\n    {title ? <title>{title}</title> : null}\n    <path d=\"M10 7a4.5 4.5 0 1 1-9 0 4.5 4.5 0 0 1 9 0\" fill=\"#25324D\" />\n    <path\n      fillRule=\"evenodd\"\n      clipRule=\"evenodd\"\n      d=\"M5.492 10C3.73 10 2.5 8.65 2.5 7.017V7c0-1.633 1.246-3 3.008-3S8.5 5.35 8.5 6.983V7c0 1.633-1.246 3-3.008 3m.016-.945c1.14 0 1.935-.911 1.935-2.038V7c0-1.127-.812-2.055-1.951-2.055s-1.935.911-1.935 2.038V7c0 1.127.812 2.055 1.951 2.055\"\n      fill=\"#548AF7\"\n    />\n    <path\n      fillRule=\"evenodd\"\n      clipRule=\"evenodd\"\n      d=\"M11.5 8a.5.5 0 0 1-.5-.5V1.707L9.854 2.854a.5.5 0 1 1-.708-.708l2-2a.5.5 0 0 1 .708 0l2 2a.5.5 0 0 1-.708.708L12 1.707V7.5a.5.5 0 0 1-.5.5\"\n      fill=\"#DB5C5C\"\n    />\n    <path\n      d=\"M10 7a4.5 4.5 0 1 1-1.578-3.422l.017-.017a1.5 1.5 0 0 1-.391-1.437 5.5 5.5 0 1 0 2.66 6.65A1.5 1.5 0 0 1 10 7.5z\"\n      fill=\"#548AF7\"\n    />\n  </svg>\n);\n\nexport const OverridingMethod: FC<OverridingMethodProps> = ({\n  size = 'md',\n  mode = 'light',\n  className,\n  'aria-label': ariaLabel,\n  title,\n  ...props\n}) => {\n  const SvgComponent =\n    mode === 'light' ? OverridingMethodLight : OverridingMethodDark;\n\n  return (\n    <SvgComponent\n      size={sizeMap[size]}\n      className={cn('inline-block flex-shrink-0', className)}\n      title={title}\n      role={ariaLabel ? 'img' : 'presentation'}\n      aria-label={ariaLabel}\n      aria-hidden={!ariaLabel}\n      {...props}\n    />\n  );\n};"
    }
  ],
  "meta": {
    "keywords": [
      "overriding-method",
      "icon",
      "editor-icons",
      "jetbrains"
    ]
  }
}