{
  "name": "icons-plugins-bdt",
  "type": "registry:ui",
  "title": "Plugins Bdt Icons",
  "description": "All 18 icons from the Plugins Bdt category.",
  "registryDependencies": [
    "utils",
    "@jetbrains-ui/icons-plugins-types"
  ],
  "files": [
    {
      "path": "registry/icons/plugins/bdt/index.ts",
      "type": "registry:ui",
      "target": "components/jetbrains-ui/icons/plugins/bdt/index.ts",
      "content": "export { ArbitraryCluster } from './arbitrary-cluster';\nexport type { ArbitraryClusterProps } from './arbitrary-cluster';\nexport { AwsGlue } from './aws-glue';\nexport type { AwsGlueProps } from './aws-glue';\nexport { ChartArea } from './chart-area';\nexport type { ChartAreaProps } from './chart-area';\nexport { ChartAreaRange } from './chart-area-range';\nexport type { ChartAreaRangeProps } from './chart-area-range';\nexport { ChartBar } from './chart-bar';\nexport type { ChartBarProps } from './chart-bar';\nexport { ChartBubble } from './chart-bubble';\nexport type { ChartBubbleProps } from './chart-bubble';\nexport { ChartHistogram } from './chart-histogram';\nexport type { ChartHistogramProps } from './chart-histogram';\nexport { ChartLine } from './chart-line';\nexport type { ChartLineProps } from './chart-line';\nexport { ChartPie } from './chart-pie';\nexport type { ChartPieProps } from './chart-pie';\nexport { ChartScatter } from './chart-scatter';\nexport type { ChartScatterProps } from './chart-scatter';\nexport { ChartStock } from './chart-stock';\nexport type { ChartStockProps } from './chart-stock';\nexport { Cluster } from './cluster';\nexport type { ClusterProps } from './cluster';\nexport { DbtUtility } from './dbt-utility';\nexport type { DbtUtilityProps } from './dbt-utility';\nexport { Flink } from './flink';\nexport type { FlinkProps } from './flink';\nexport { PySpark } from './py-spark';\nexport type { PySparkProps } from './py-spark';\nexport { RemoteFileSystems } from './remote-file-systems';\nexport type { RemoteFileSystemsProps } from './remote-file-systems';\nexport { SparkRun } from './spark-run';\nexport type { SparkRunProps } from './spark-run';\nexport { Zeppelin } from './zeppelin';\nexport type { ZeppelinProps } from './zeppelin';"
    },
    {
      "path": "registry/icons/plugins/bdt/arbitrary-cluster/index.tsx",
      "type": "registry:ui",
      "target": "components/jetbrains-ui/icons/plugins/bdt/arbitrary-cluster/index.tsx",
      "content": "import React from 'react';\nimport { cn } from '@/lib/utils';\nimport { type IconProps, type SvgProps, sizeMap } from '../../types';\n\nexport type ArbitraryClusterProps = IconProps;\n\nconst ArbitraryClusterLight: React.FC<SvgProps> = ({\n  size,\n  className,\n  title,\n  role,\n  'aria-label': ariaLabel,\n  'aria-hidden': ariaHidden,\n}) => (\n  <svg\n    width={size}\n    height={size}\n    viewBox=\"0 0 16 16\"\n    fill=\"none\"\n    xmlns=\"http://www.w3.org/2000/svg\"\n    className={className}\n    role={role}\n    aria-label={ariaLabel}\n    aria-hidden={ariaHidden}\n  >\n    {title && <title>{title}</title>}\n    <path d=\"M11.999 13a1 1 0 1 0 0-2 1 1 0 0 0 0 2\" fill=\"#3574F0\" />\n    <path\n      fillRule=\"evenodd\"\n      clipRule=\"evenodd\"\n      d=\"M13.12 15.676a.5.5 0 0 1-.468.324h-1.307a.5.5 0 0 1-.468-.324l-.25-.666a.5.5 0 0 0-.55-.317l-.7.116a.5.5 0 0 1-.516-.243l-.653-1.132a.5.5 0 0 1 .047-.568l.45-.548a.5.5 0 0 0 0-.636l-.45-.548a.5.5 0 0 1-.047-.568l.653-1.132a.5.5 0 0 1 .515-.243l.701.116a.5.5 0 0 0 .55-.317l.25-.666A.5.5 0 0 1 11.345 8h1.307a.5.5 0 0 1 .468.324l.25.666a.5.5 0 0 0 .55.317l.7-.116a.5.5 0 0 1 .516.243l.653 1.132a.5.5 0 0 1-.047.568l-.451.548a.5.5 0 0 0 0 .636l.451.548a.5.5 0 0 1 .047.568l-.653 1.132a.5.5 0 0 1-.515.243l-.701-.116a.5.5 0 0 0-.55.317zM11.692 15h.614l.127-.34a1.5 1.5 0 0 1 1.65-.954l.36.06.307-.532-.231-.281a1.5 1.5 0 0 1 0-1.906l.231-.281-.307-.532-.36.06a1.5 1.5 0 0 1-1.65-.953L12.306 9h-.614l-.128.34a1.5 1.5 0 0 1-1.651.954l-.36-.06-.306.532.231.281a1.5 1.5 0 0 1 0 1.906l-.231.281.307.532.359-.06a1.5 1.5 0 0 1 1.65.953z\"\n      fill=\"#3574F0\"\n    />\n    <path\n      fillRule=\"evenodd\"\n      clipRule=\"evenodd\"\n      d=\"M12.309 15h-.614l-.128-.34a1.5 1.5 0 0 0-1.65-.954l-.36.06-.307-.532.231-.281a1.5 1.5 0 0 0 0-1.906l-.231-.281.307-.532.36.06a1.5 1.5 0 0 0 1.65-.953L11.695 9h.614l.127.34a1.5 1.5 0 0 0 1.651.954l.36-.06.306.532-.231.281a1.5 1.5 0 0 0 0 1.906l.231.281-.307.532-.359-.06a1.5 1.5 0 0 0-1.65.953zm.693-3a1 1 0 1 1-2 0 1 1 0 0 1 2 0\"\n      fill=\"#EDF3FF\"\n    />\n    <path\n      d=\"M9 3a1 1 0 1 1-2 0 1 1 0 0 1 2 0M3 7.5a1 1 0 1 0 0-2 1 1 0 0 0 0 2M12.135 7.002a5 5 0 0 1 1.5.271 1 1 0 1 0-1.5-.271M5 13a1 1 0 1 0 0-2 1 1 0 0 0 0 2\"\n      fill=\"#EBECF0\"\n    />\n    <path\n      fillRule=\"evenodd\"\n      clipRule=\"evenodd\"\n      d=\"M9.874 3.701a2 2 0 1 0-3.747 0L4.3 4.98A2 2 0 1 0 3.192 8.49l.676 1.86a2 2 0 1 0 .94-.342l-.676-1.86a2 2 0 0 0 .742-2.35L6.7 4.52c.35.3.804.48 1.3.48s.95-.18 1.3-.48L11.126 5.8a2 2 0 0 0-.04 1.284 5 5 0 0 1 1.049-.081 1 1 0 1 1 1.5.271q.502.175.95.446A2 2 0 0 0 11.7 4.98zm-.878-.614Q9 3.043 9 3a1 1 0 1 0-.004.087m-5.23 4.056A1 1 0 0 1 3 7.5a1 1 0 1 1 .766-.357M5 13a1 1 0 1 0 0-2 1 1 0 0 0 0 2\"\n      fill=\"#6C707E\"\n    />\n  </svg>\n);\n\nconst ArbitraryClusterDark: React.FC<SvgProps> = ({\n  size,\n  className,\n  title,\n  role,\n  'aria-label': ariaLabel,\n  'aria-hidden': ariaHidden,\n}) => (\n  <svg\n    width={size}\n    height={size}\n    viewBox=\"0 0 16 16\"\n    fill=\"none\"\n    xmlns=\"http://www.w3.org/2000/svg\"\n    className={className}\n    role={role}\n    aria-label={ariaLabel}\n    aria-hidden={ariaHidden}\n  >\n    {title && <title>{title}</title>}\n    <path d=\"M11.999 13a1 1 0 1 0 0-2 1 1 0 0 0 0 2\" fill=\"#548AF7\" />\n    <path\n      fillRule=\"evenodd\"\n      clipRule=\"evenodd\"\n      d=\"M13.12 15.676a.5.5 0 0 1-.468.324h-1.307a.5.5 0 0 1-.468-.324l-.25-.666a.5.5 0 0 0-.55-.317l-.7.116a.5.5 0 0 1-.516-.243l-.653-1.132a.5.5 0 0 1 .047-.568l.45-.548a.5.5 0 0 0 0-.636l-.45-.548a.5.5 0 0 1-.047-.568l.653-1.132a.5.5 0 0 1 .515-.243l.701.116a.5.5 0 0 0 .55-.317l.25-.666A.5.5 0 0 1 11.345 8h1.307a.5.5 0 0 1 .468.324l.25.666a.5.5 0 0 0 .55.317l.7-.116a.5.5 0 0 1 .516.243l.653 1.132a.5.5 0 0 1-.047.568l-.451.548a.5.5 0 0 0 0 .636l.451.548a.5.5 0 0 1 .047.568l-.653 1.132a.5.5 0 0 1-.515.243l-.701-.116a.5.5 0 0 0-.55.317zM11.692 15h.614l.127-.34a1.5 1.5 0 0 1 1.65-.954l.36.06.307-.532-.231-.281a1.5 1.5 0 0 1 0-1.906l.231-.281-.307-.532-.36.06a1.5 1.5 0 0 1-1.65-.953L12.306 9h-.614l-.128.34a1.5 1.5 0 0 1-1.651.954l-.36-.06-.306.532.231.281a1.5 1.5 0 0 1 0 1.906l-.231.281.307.532.359-.06a1.5 1.5 0 0 1 1.65.953z\"\n      fill=\"#548AF7\"\n    />\n    <path\n      fillRule=\"evenodd\"\n      clipRule=\"evenodd\"\n      d=\"M12.309 15h-.614l-.128-.34a1.5 1.5 0 0 0-1.65-.954l-.36.06-.307-.532.231-.281a1.5 1.5 0 0 0 0-1.906l-.231-.281.307-.532.36.06a1.5 1.5 0 0 0 1.65-.953L11.695 9h.614l.127.34a1.5 1.5 0 0 0 1.651.954l.36-.06.306.532-.231.281a1.5 1.5 0 0 0 0 1.906l.231.281-.307.532-.359-.06a1.5 1.5 0 0 0-1.65.953zm.693-3a1 1 0 1 1-2 0 1 1 0 0 1 2 0\"\n      fill=\"#25324D\"\n    />\n    <path\n      d=\"M9 3a1 1 0 1 1-2 0 1 1 0 0 1 2 0M3 7.5a1 1 0 1 0 0-2 1 1 0 0 0 0 2M12.135 7.002a5 5 0 0 1 1.5.271 1 1 0 1 0-1.5-.271M5 13a1 1 0 1 0 0-2 1 1 0 0 0 0 2\"\n      fill=\"#43454A\"\n    />\n    <path\n      fillRule=\"evenodd\"\n      clipRule=\"evenodd\"\n      d=\"M9.874 3.701a2 2 0 1 0-3.747 0L4.3 4.98A2 2 0 1 0 3.192 8.49l.676 1.86a2 2 0 1 0 .94-.342l-.676-1.86a2 2 0 0 0 .742-2.35L6.7 4.52c.35.3.804.48 1.3.48s.95-.18 1.3-.48L11.126 5.8a2 2 0 0 0-.04 1.284 5 5 0 0 1 1.049-.081 1 1 0 1 1 1.5.271q.502.175.95.446A2 2 0 0 0 11.7 4.98zm-.878-.614Q9 3.043 9 3a1 1 0 1 0-.004.087m-5.23 4.056A1 1 0 0 1 3 7.5a1 1 0 1 1 .766-.357M5 13a1 1 0 1 0 0-2 1 1 0 0 0 0 2\"\n      fill=\"#CED0D6\"\n    />\n  </svg>\n);\n\nexport const ArbitraryCluster: React.FC<ArbitraryClusterProps> = ({\n  size = 'md',\n  mode = 'light',\n  className,\n  'aria-label': ariaLabel,\n  title,\n  ...props\n}) => {\n  const SvgComponent =\n    mode === 'light' ? ArbitraryClusterLight : ArbitraryClusterDark;\n\n  return (\n    <SvgComponent\n      size={sizeMap[size]}\n      className={cn('inline-block flex-shrink-0', className)}\n      title={title}\n      role={ariaLabel ? 'img' : 'presentation'}\n      aria-label={ariaLabel}\n      aria-hidden={!ariaLabel}\n      {...props}\n    />\n  );\n};"
    },
    {
      "path": "registry/icons/plugins/bdt/aws-glue/index.tsx",
      "type": "registry:ui",
      "target": "components/jetbrains-ui/icons/plugins/bdt/aws-glue/index.tsx",
      "content": "import React from 'react';\nimport { cn } from '@/lib/utils';\nimport { type IconProps, type SvgProps, sizeMap } from '../../types';\n\nexport type AwsGlueProps = IconProps;\n\nconst AwsGlueLight: React.FC<SvgProps> = ({\n  size,\n  className,\n  title,\n  role,\n  'aria-label': ariaLabel,\n  'aria-hidden': ariaHidden,\n}) => (\n  <svg\n    width={size}\n    height={size}\n    viewBox=\"0 0 16 16\"\n    fill=\"none\"\n    xmlns=\"http://www.w3.org/2000/svg\"\n    className={className}\n    role={role}\n    aria-label={ariaLabel}\n    aria-hidden={ariaHidden}\n  >\n    {title && <title>{title}</title>}\n    <path d=\"m12.773 5.144 1.23.37v1.59l-1.23-.089z\" fill=\"#F58435\" />\n    <path\n      d=\"M11.113 5.397v1.716l1.659-.098V5.144zM3.219 4.276 2 4.656v2.496l1.219-.098z\"\n      fill=\"#9D5025\"\n    />\n    <path d=\"M4.887 4.53v2.622L3.22 7.054V4.276z\" fill=\"#E66D17\" />\n    <path d=\"M13.999 8v2l-5.995 1.51V8.049z\" fill=\"#F58435\" />\n    <path d=\"M2 8v2l6.005 1.51V8.049z\" fill=\"#9D5025\" />\n    <path d=\"m8.004 1 1.768.848v4.914l-1.768-.156z\" fill=\"#F58435\" />\n    <path d=\"m8.005 1-1.778.868v4.904l1.778-.166z\" fill=\"#9D5025\" />\n    <path d=\"M9.762 12.446v1.716L8.004 15V13.1z\" fill=\"#F58435\" />\n    <path d=\"M6.246 12.446v1.716L8.005 15V13.1z\" fill=\"#9D5025\" />\n    <path d=\"m8.005 11.949 1.758.496-1.758.653-1.759-.653z\" fill=\"#FEB57E\" />\n  </svg>\n);\n\nconst AwsGlueDark: React.FC<SvgProps> = ({\n  size,\n  className,\n  title,\n  role,\n  'aria-label': ariaLabel,\n  'aria-hidden': ariaHidden,\n}) => (\n  <svg\n    width={size}\n    height={size}\n    viewBox=\"0 0 16 16\"\n    fill=\"none\"\n    xmlns=\"http://www.w3.org/2000/svg\"\n    className={className}\n    role={role}\n    aria-label={ariaLabel}\n    aria-hidden={ariaHidden}\n  >\n    {title && <title>{title}</title>}\n    <path d=\"m12.773 5.144 1.23.37v1.59l-1.23-.089z\" fill=\"#F58435\" />\n    <path\n      d=\"M11.113 5.397v1.716l1.659-.098V5.144zM3.219 4.276 2 4.656v2.496l1.219-.098z\"\n      fill=\"#9D5025\"\n    />\n    <path\n      d=\"M4.887 4.53v2.622L3.22 7.054V4.276zM13.999 8v2l-5.995 1.51V8.049z\"\n      fill=\"#F58435\"\n    />\n    <path d=\"M2 8v2l6.005 1.51V8.049z\" fill=\"#9D5025\" />\n    <path d=\"m8.004 1 1.768.848v4.914l-1.768-.156z\" fill=\"#F58435\" />\n    <path d=\"m8.005 1-1.778.868v4.904l1.778-.166z\" fill=\"#9D5025\" />\n    <path d=\"M9.762 12.446v1.716L8.004 15V13.1z\" fill=\"#F58435\" />\n    <path d=\"M6.246 12.446v1.716L8.005 15V13.1z\" fill=\"#9D5025\" />\n    <path d=\"m8.005 11.949 1.758.496-1.758.653-1.759-.653z\" fill=\"#FEB57E\" />\n  </svg>\n);\n\nexport const AwsGlue: React.FC<AwsGlueProps> = ({\n  size = 'md',\n  mode = 'light',\n  className,\n  'aria-label': ariaLabel,\n  title,\n  ...props\n}) => {\n  const SvgComponent = mode === 'light' ? AwsGlueLight : AwsGlueDark;\n\n  return (\n    <SvgComponent\n      size={sizeMap[size]}\n      className={cn('inline-block flex-shrink-0', className)}\n      title={title}\n      role={ariaLabel ? 'img' : 'presentation'}\n      aria-label={ariaLabel}\n      aria-hidden={!ariaLabel}\n      {...props}\n    />\n  );\n};"
    },
    {
      "path": "registry/icons/plugins/bdt/chart-area/index.tsx",
      "type": "registry:ui",
      "target": "components/jetbrains-ui/icons/plugins/bdt/chart-area/index.tsx",
      "content": "import React from 'react';\nimport { cn } from '@/lib/utils';\nimport { type IconProps, type SvgProps, sizeMap } from '../../types';\n\nexport type ChartAreaProps = IconProps;\n\nconst ChartAreaLight: React.FC<SvgProps> = ({\n  size,\n  className,\n  title,\n  role,\n  'aria-label': ariaLabel,\n  'aria-hidden': ariaHidden,\n}) => (\n  <svg\n    width={size}\n    height={size}\n    viewBox=\"0 0 16 16\"\n    fill=\"none\"\n    xmlns=\"http://www.w3.org/2000/svg\"\n    className={className}\n    role={role}\n    aria-label={ariaLabel}\n    aria-hidden={ariaHidden}\n  >\n    {title && <title>{title}</title>}\n    <path\n      d=\"M2 2.5a.5.5 0 0 0-1 0V13a1 1 0 0 0 1 1h12a1 1 0 0 0 1-1H2z\"\n      fill=\"#6C707E\"\n    />\n    <path\n      d=\"m2 4.86 2.5 2 4.375-3.5a1 1 0 0 1 1.25 0l4.5 3.6a1 1 0 0 1 .375.78V13H2h12V7.74l-4.5-3.6-4.375 3.5a1 1 0 0 1-1.25 0L2 6.14z\"\n      fill=\"#3574F0\"\n    />\n    <path\n      d=\"M2 6.14V13h12.5-.5V7.74l-4.5-3.6-4.375 3.5a1 1 0 0 1-1.25 0z\"\n      fill=\"#EDF3FF\"\n    />\n  </svg>\n);\n\nconst ChartAreaDark: React.FC<SvgProps> = ({\n  size,\n  className,\n  title,\n  role,\n  'aria-label': ariaLabel,\n  'aria-hidden': ariaHidden,\n}) => (\n  <svg\n    width={size}\n    height={size}\n    viewBox=\"0 0 16 16\"\n    fill=\"none\"\n    xmlns=\"http://www.w3.org/2000/svg\"\n    className={className}\n    role={role}\n    aria-label={ariaLabel}\n    aria-hidden={ariaHidden}\n  >\n    {title && <title>{title}</title>}\n    <path\n      d=\"M2 2.5a.5.5 0 0 0-1 0V13a1 1 0 0 0 1 1h12a1 1 0 0 0 1-1H2z\"\n      fill=\"#CED0D6\"\n    />\n    <path\n      d=\"m2 4.86 2.5 2 4.375-3.5a1 1 0 0 1 1.25 0l4.5 3.6a1 1 0 0 1 .375.78V13H2h12V7.74l-4.5-3.6-4.375 3.5a1 1 0 0 1-1.25 0L2 6.14z\"\n      fill=\"#548AF7\"\n    />\n    <path\n      d=\"M2 6.14V13h12.5-.5V7.74l-4.5-3.6-4.375 3.5a1 1 0 0 1-1.25 0z\"\n      fill=\"#25324D\"\n    />\n  </svg>\n);\n\nexport const ChartArea: React.FC<ChartAreaProps> = ({\n  size = 'md',\n  mode = 'light',\n  className,\n  'aria-label': ariaLabel,\n  title,\n  ...props\n}) => {\n  const SvgComponent = mode === 'light' ? ChartAreaLight : ChartAreaDark;\n\n  return (\n    <SvgComponent\n      size={sizeMap[size]}\n      className={cn('inline-block flex-shrink-0', className)}\n      title={title}\n      role={ariaLabel ? 'img' : 'presentation'}\n      aria-label={ariaLabel}\n      aria-hidden={!ariaLabel}\n      {...props}\n    />\n  );\n};"
    },
    {
      "path": "registry/icons/plugins/bdt/chart-area-range/index.tsx",
      "type": "registry:ui",
      "target": "components/jetbrains-ui/icons/plugins/bdt/chart-area-range/index.tsx",
      "content": "import React from 'react';\nimport { cn } from '@/lib/utils';\nimport { type IconProps, type SvgProps, sizeMap } from '../../types';\n\nexport type ChartAreaRangeProps = IconProps;\n\nconst ChartAreaRangeLight: React.FC<SvgProps> = ({\n  size,\n  className,\n  title,\n  role,\n  'aria-label': ariaLabel,\n  'aria-hidden': ariaHidden,\n}) => (\n  <svg\n    width={size}\n    height={size}\n    viewBox=\"0 0 16 16\"\n    fill=\"none\"\n    xmlns=\"http://www.w3.org/2000/svg\"\n    className={className}\n    role={role}\n    aria-label={ariaLabel}\n    aria-hidden={ariaHidden}\n  >\n    {title && <title>{title}</title>}\n    <path\n      d=\"m9.5 3.14 4.5 3.6v3.72l-3.875-3.1a1 1 0 0 0-1.25 0L4.5 10.86l-2.5-2V5.14l1.875 1.5a1 1 0 0 0 1.25 0z\"\n      fill=\"#EDF3FF\"\n    />\n    <path\n      d=\"M2 2.5a.5.5 0 0 0-1 0V13a1 1 0 0 0 1 1h12.5a.5.5 0 0 0 0-1H2z\"\n      fill=\"#6C707E\"\n    />\n    <path\n      d=\"m2 3.86 2.5 2 4.375-3.5a1 1 0 0 1 1.25 0l4.687 3.75A.5.5 0 0 1 15 6.5v5a.5.5 0 0 1-.812.39L9.5 8.14l-4.375 3.5a1 1 0 0 1-1.25 0L2 10.14V8.86l2.5 2 4.375-3.5a1 1 0 0 1 1.25 0L14 10.46V6.74l-4.5-3.6-4.375 3.5a1 1 0 0 1-1.25 0L2 5.14z\"\n      fill=\"#3574F0\"\n    />\n  </svg>\n);\n\nconst ChartAreaRangeDark: React.FC<SvgProps> = ({\n  size,\n  className,\n  title,\n  role,\n  'aria-label': ariaLabel,\n  'aria-hidden': ariaHidden,\n}) => (\n  <svg\n    width={size}\n    height={size}\n    viewBox=\"0 0 16 16\"\n    fill=\"none\"\n    xmlns=\"http://www.w3.org/2000/svg\"\n    className={className}\n    role={role}\n    aria-label={ariaLabel}\n    aria-hidden={ariaHidden}\n  >\n    {title && <title>{title}</title>}\n    <path\n      d=\"m9.5 3.14 4.5 3.6v3.72l-3.875-3.1a1 1 0 0 0-1.25 0L4.5 10.86l-2.5-2V5.14l1.875 1.5a1 1 0 0 0 1.25 0z\"\n      fill=\"#25324D\"\n    />\n    <path\n      d=\"M2 2.5a.5.5 0 0 0-1 0V13a1 1 0 0 0 1 1h12.5a.5.5 0 0 0 0-1H2z\"\n      fill=\"#CED0D6\"\n    />\n    <path\n      d=\"m2 3.86 2.5 2 4.375-3.5a1 1 0 0 1 1.25 0l4.687 3.75A.5.5 0 0 1 15 6.5v5a.5.5 0 0 1-.812.39L9.5 8.14l-4.375 3.5a1 1 0 0 1-1.25 0L2 10.14V8.86l2.5 2 4.375-3.5a1 1 0 0 1 1.25 0L14 10.46V6.74l-4.5-3.6-4.375 3.5a1 1 0 0 1-1.25 0L2 5.14z\"\n      fill=\"#548AF7\"\n    />\n  </svg>\n);\n\nexport const ChartAreaRange: React.FC<ChartAreaRangeProps> = ({\n  size = 'md',\n  mode = 'light',\n  className,\n  'aria-label': ariaLabel,\n  title,\n  ...props\n}) => {\n  const SvgComponent =\n    mode === 'light' ? ChartAreaRangeLight : ChartAreaRangeDark;\n\n  return (\n    <SvgComponent\n      size={sizeMap[size]}\n      className={cn('inline-block flex-shrink-0', className)}\n      title={title}\n      role={ariaLabel ? 'img' : 'presentation'}\n      aria-label={ariaLabel}\n      aria-hidden={!ariaLabel}\n      {...props}\n    />\n  );\n};"
    },
    {
      "path": "registry/icons/plugins/bdt/chart-bar/index.tsx",
      "type": "registry:ui",
      "target": "components/jetbrains-ui/icons/plugins/bdt/chart-bar/index.tsx",
      "content": "import React from 'react';\nimport { cn } from '@/lib/utils';\nimport { type IconProps, type SvgProps, sizeMap } from '../../types';\n\nexport type ChartBarProps = IconProps;\n\nconst ChartBarLight: React.FC<SvgProps> = ({\n  size,\n  className,\n  title,\n  role,\n  'aria-label': ariaLabel,\n  'aria-hidden': ariaHidden,\n}) => (\n  <svg\n    width={size}\n    height={size}\n    viewBox=\"0 0 16 16\"\n    fill=\"none\"\n    xmlns=\"http://www.w3.org/2000/svg\"\n    className={className}\n    role={role}\n    aria-label={ariaLabel}\n    aria-hidden={ariaHidden}\n  >\n    {title && <title>{title}</title>}\n    <path\n      fillRule=\"evenodd\"\n      clipRule=\"evenodd\"\n      d=\"M6 3a1 1 0 0 1 1-1h2a1 1 0 0 1 1 1v10a1 1 0 0 1-1 1H7a1 1 0 0 1-1-1zm3 0H7v10h2z\"\n      fill=\"#3574F0\"\n    />\n    <path d=\"M7 3h2v10H7z\" fill=\"#EDF3FF\" />\n    <path\n      fillRule=\"evenodd\"\n      clipRule=\"evenodd\"\n      d=\"M12 5a1 1 0 0 0-1 1v7a1 1 0 0 0 1 1h2a1 1 0 0 0 1-1V6a1 1 0 0 0-1-1zm0 1h2v7h-2zM2 7a1 1 0 0 0-1 1v5a1 1 0 0 0 1 1h2a1 1 0 0 0 1-1V8a1 1 0 0 0-1-1zm0 1h2v5H2z\"\n      fill=\"#6C707E\"\n    />\n    <path d=\"M14 6h-2v7h2zM4 8H2v5h2z\" fill=\"#EBECF0\" />\n  </svg>\n);\n\nconst ChartBarDark: React.FC<SvgProps> = ({\n  size,\n  className,\n  title,\n  role,\n  'aria-label': ariaLabel,\n  'aria-hidden': ariaHidden,\n}) => (\n  <svg\n    width={size}\n    height={size}\n    viewBox=\"0 0 16 16\"\n    fill=\"none\"\n    xmlns=\"http://www.w3.org/2000/svg\"\n    className={className}\n    role={role}\n    aria-label={ariaLabel}\n    aria-hidden={ariaHidden}\n  >\n    {title && <title>{title}</title>}\n    <path\n      fillRule=\"evenodd\"\n      clipRule=\"evenodd\"\n      d=\"M6 3a1 1 0 0 1 1-1h2a1 1 0 0 1 1 1v10a1 1 0 0 1-1 1H7a1 1 0 0 1-1-1zm3 0H7v10h2z\"\n      fill=\"#548AF7\"\n    />\n    <path d=\"M7 3h2v10H7z\" fill=\"#25324D\" />\n    <path\n      fillRule=\"evenodd\"\n      clipRule=\"evenodd\"\n      d=\"M12 5a1 1 0 0 0-1 1v7a1 1 0 0 0 1 1h2a1 1 0 0 0 1-1V6a1 1 0 0 0-1-1zm0 1h2v7h-2zM2 7a1 1 0 0 0-1 1v5a1 1 0 0 0 1 1h2a1 1 0 0 0 1-1V8a1 1 0 0 0-1-1zm0 1h2v5H2z\"\n      fill=\"#CED0D6\"\n    />\n    <path d=\"M14 6h-2v7h2zM4 8H2v5h2z\" fill=\"#43454A\" />\n  </svg>\n);\n\nexport const ChartBar: React.FC<ChartBarProps> = ({\n  size = 'md',\n  mode = 'light',\n  className,\n  'aria-label': ariaLabel,\n  title,\n  ...props\n}) => {\n  const SvgComponent = mode === 'light' ? ChartBarLight : ChartBarDark;\n\n  return (\n    <SvgComponent\n      size={sizeMap[size]}\n      className={cn('inline-block flex-shrink-0', className)}\n      title={title}\n      role={ariaLabel ? 'img' : 'presentation'}\n      aria-label={ariaLabel}\n      aria-hidden={!ariaLabel}\n      {...props}\n    />\n  );\n};"
    },
    {
      "path": "registry/icons/plugins/bdt/chart-bubble/index.tsx",
      "type": "registry:ui",
      "target": "components/jetbrains-ui/icons/plugins/bdt/chart-bubble/index.tsx",
      "content": "import React from 'react';\nimport { cn } from '@/lib/utils';\nimport { type IconProps, type SvgProps, sizeMap } from '../../types';\n\nexport type ChartBubbleProps = IconProps;\n\nconst ChartBubbleLight: React.FC<SvgProps> = ({\n  size,\n  className,\n  title,\n  role,\n  'aria-label': ariaLabel,\n  'aria-hidden': ariaHidden,\n}) => (\n  <svg\n    width={size}\n    height={size}\n    viewBox=\"0 0 16 16\"\n    fill=\"none\"\n    xmlns=\"http://www.w3.org/2000/svg\"\n    className={className}\n    role={role}\n    aria-label={ariaLabel}\n    aria-hidden={ariaHidden}\n  >\n    {title && <title>{title}</title>}\n    <path\n      d=\"M1.5 2a.5.5 0 0 1 .5.5V13h12.5a.5.5 0 0 1 0 1H2a1 1 0 0 1-1-1V2.5a.5.5 0 0 1 .5-.5\"\n      fill=\"#6C707E\"\n    />\n    <circle cx=\"8.5\" cy=\"4.5\" r=\"2\" fill=\"#EDF3FF\" stroke=\"#3574F0\" />\n    <circle cx=\"13\" cy=\"8\" r=\"1.5\" fill=\"#EDF3FF\" stroke=\"#3574F0\" />\n    <circle cx=\"5.5\" cy=\"9.5\" r=\"1\" fill=\"#EDF3FF\" stroke=\"#3574F0\" />\n  </svg>\n);\n\nconst ChartBubbleDark: React.FC<SvgProps> = ({\n  size,\n  className,\n  title,\n  role,\n  'aria-label': ariaLabel,\n  'aria-hidden': ariaHidden,\n}) => (\n  <svg\n    width={size}\n    height={size}\n    viewBox=\"0 0 16 16\"\n    fill=\"none\"\n    xmlns=\"http://www.w3.org/2000/svg\"\n    className={className}\n    role={role}\n    aria-label={ariaLabel}\n    aria-hidden={ariaHidden}\n  >\n    {title && <title>{title}</title>}\n    <path\n      d=\"M1.5 2a.5.5 0 0 1 .5.5V13h12.5a.5.5 0 0 1 0 1H2a1 1 0 0 1-1-1V2.5a.5.5 0 0 1 .5-.5\"\n      fill=\"#CED0D6\"\n    />\n    <circle cx=\"8.5\" cy=\"4.5\" r=\"2\" fill=\"#25324D\" stroke=\"#548AF7\" />\n    <circle cx=\"13\" cy=\"8\" r=\"1.5\" fill=\"#25324D\" stroke=\"#548AF7\" />\n    <circle cx=\"5.5\" cy=\"9.5\" r=\"1\" fill=\"#25324D\" stroke=\"#548AF7\" />\n  </svg>\n);\n\nexport const ChartBubble: React.FC<ChartBubbleProps> = ({\n  size = 'md',\n  mode = 'light',\n  className,\n  'aria-label': ariaLabel,\n  title,\n  ...props\n}) => {\n  const SvgComponent = mode === 'light' ? ChartBubbleLight : ChartBubbleDark;\n\n  return (\n    <SvgComponent\n      size={sizeMap[size]}\n      className={cn('inline-block flex-shrink-0', className)}\n      title={title}\n      role={ariaLabel ? 'img' : 'presentation'}\n      aria-label={ariaLabel}\n      aria-hidden={!ariaLabel}\n      {...props}\n    />\n  );\n};"
    },
    {
      "path": "registry/icons/plugins/bdt/chart-histogram/index.tsx",
      "type": "registry:ui",
      "target": "components/jetbrains-ui/icons/plugins/bdt/chart-histogram/index.tsx",
      "content": "import React from 'react';\nimport { cn } from '@/lib/utils';\nimport { type IconProps, type SvgProps, sizeMap } from '../../types';\n\nexport type ChartHistogramProps = IconProps;\n\nconst ChartHistogramLight: React.FC<SvgProps> = ({\n  size,\n  className,\n  title,\n  role,\n  'aria-label': ariaLabel,\n  'aria-hidden': ariaHidden,\n}) => (\n  <svg\n    width={size}\n    height={size}\n    viewBox=\"0 0 16 16\"\n    fill=\"none\"\n    xmlns=\"http://www.w3.org/2000/svg\"\n    className={className}\n    role={role}\n    aria-label={ariaLabel}\n    aria-hidden={ariaHidden}\n  >\n    {title && <title>{title}</title>}\n    <path\n      fillRule=\"evenodd\"\n      clipRule=\"evenodd\"\n      d=\"M4 3a1 1 0 0 1 1-1h2a1 1 0 0 1 1 1v11H4zm3 0H5v10h2z\"\n      fill=\"#3574F0\"\n    />\n    <path d=\"M5 3h2v10H5z\" fill=\"#EDF3FF\" />\n    <path d=\"M8 6v7h2V6zM11 13V9h2v4zM4 13V8H2v5z\" fill=\"#EBECF0\" />\n    <path\n      fillRule=\"evenodd\"\n      clipRule=\"evenodd\"\n      d=\"M13 14H2a1 1 0 0 1-1-1V8a1 1 0 0 1 1-1h2v1H2v5h8V6H8V5h2a1 1 0 0 1 1 1v2h2a1 1 0 0 1 1 1v4a1 1 0 0 1-1 1m-2-1V9h2v4z\"\n      fill=\"#6C707E\"\n    />\n  </svg>\n);\n\nconst ChartHistogramDark: React.FC<SvgProps> = ({\n  size,\n  className,\n  title,\n  role,\n  'aria-label': ariaLabel,\n  'aria-hidden': ariaHidden,\n}) => (\n  <svg\n    width={size}\n    height={size}\n    viewBox=\"0 0 16 16\"\n    fill=\"none\"\n    xmlns=\"http://www.w3.org/2000/svg\"\n    className={className}\n    role={role}\n    aria-label={ariaLabel}\n    aria-hidden={ariaHidden}\n  >\n    {title && <title>{title}</title>}\n    <path\n      fillRule=\"evenodd\"\n      clipRule=\"evenodd\"\n      d=\"M4 3a1 1 0 0 1 1-1h2a1 1 0 0 1 1 1v11H4zm3 0H5v10h2z\"\n      fill=\"#548AF7\"\n    />\n    <path d=\"M5 3h2v10H5z\" fill=\"#25324D\" />\n    <path d=\"M8 6v7h2V6zM11 13V9h2v4zM4 13V8H2v5z\" fill=\"#43454A\" />\n    <path\n      fillRule=\"evenodd\"\n      clipRule=\"evenodd\"\n      d=\"M13 14H2a1 1 0 0 1-1-1V8a1 1 0 0 1 1-1h2v1H2v5h8V6H8V5h2a1 1 0 0 1 1 1v2h2a1 1 0 0 1 1 1v4a1 1 0 0 1-1 1m-2-1V9h2v4z\"\n      fill=\"#CED0D6\"\n    />\n  </svg>\n);\n\nexport const ChartHistogram: React.FC<ChartHistogramProps> = ({\n  size = 'md',\n  mode = 'light',\n  className,\n  'aria-label': ariaLabel,\n  title,\n  ...props\n}) => {\n  const SvgComponent =\n    mode === 'light' ? ChartHistogramLight : ChartHistogramDark;\n\n  return (\n    <SvgComponent\n      size={sizeMap[size]}\n      className={cn('inline-block flex-shrink-0', className)}\n      title={title}\n      role={ariaLabel ? 'img' : 'presentation'}\n      aria-label={ariaLabel}\n      aria-hidden={!ariaLabel}\n      {...props}\n    />\n  );\n};"
    },
    {
      "path": "registry/icons/plugins/bdt/chart-line/index.tsx",
      "type": "registry:ui",
      "target": "components/jetbrains-ui/icons/plugins/bdt/chart-line/index.tsx",
      "content": "import React from 'react';\nimport { cn } from '@/lib/utils';\nimport { type IconProps, type SvgProps, sizeMap } from '../../types';\n\nexport type ChartLineProps = IconProps;\n\nconst ChartLineLight: React.FC<SvgProps> = ({\n  size,\n  className,\n  title,\n  role,\n  'aria-label': ariaLabel,\n  'aria-hidden': ariaHidden,\n}) => (\n  <svg\n    width={size}\n    height={size}\n    viewBox=\"0 0 16 16\"\n    fill=\"none\"\n    xmlns=\"http://www.w3.org/2000/svg\"\n    className={className}\n    role={role}\n    aria-label={ariaLabel}\n    aria-hidden={ariaHidden}\n  >\n    {title && <title>{title}</title>}\n    <path\n      d=\"M1.5 2a.5.5 0 0 1 .5.5V13h12.5a.5.5 0 0 1 0 1H2a1 1 0 0 1-1-1V2.5a.5.5 0 0 1 .5-.5\"\n      fill=\"#6C707E\"\n    />\n    <path\n      d=\"M14.854 4.854a.5.5 0 0 0-.708-.708L9.5 8.793 6.207 5.5a1 1 0 0 0-1.414 0L2 8.293v1.414l3.5-3.5L8.793 9.5a1 1 0 0 0 1.414 0z\"\n      fill=\"#3574F0\"\n    />\n  </svg>\n);\n\nconst ChartLineDark: React.FC<SvgProps> = ({\n  size,\n  className,\n  title,\n  role,\n  'aria-label': ariaLabel,\n  'aria-hidden': ariaHidden,\n}) => (\n  <svg\n    width={size}\n    height={size}\n    viewBox=\"0 0 16 16\"\n    fill=\"none\"\n    xmlns=\"http://www.w3.org/2000/svg\"\n    className={className}\n    role={role}\n    aria-label={ariaLabel}\n    aria-hidden={ariaHidden}\n  >\n    {title && <title>{title}</title>}\n    <path\n      d=\"M1.5 2a.5.5 0 0 1 .5.5V13h12.5a.5.5 0 0 1 0 1H2a1 1 0 0 1-1-1V2.5a.5.5 0 0 1 .5-.5\"\n      fill=\"#CED0D6\"\n    />\n    <path\n      d=\"M14.854 4.854a.5.5 0 0 0-.708-.708L9.5 8.793 6.207 5.5a1 1 0 0 0-1.414 0L2 8.293v1.414l3.5-3.5L8.793 9.5a1 1 0 0 0 1.414 0z\"\n      fill=\"#548AF7\"\n    />\n  </svg>\n);\n\nexport const ChartLine: React.FC<ChartLineProps> = ({\n  size = 'md',\n  mode = 'light',\n  className,\n  'aria-label': ariaLabel,\n  title,\n  ...props\n}) => {\n  const SvgComponent = mode === 'light' ? ChartLineLight : ChartLineDark;\n\n  return (\n    <SvgComponent\n      size={sizeMap[size]}\n      className={cn('inline-block flex-shrink-0', className)}\n      title={title}\n      role={ariaLabel ? 'img' : 'presentation'}\n      aria-label={ariaLabel}\n      aria-hidden={!ariaLabel}\n      {...props}\n    />\n  );\n};"
    },
    {
      "path": "registry/icons/plugins/bdt/chart-pie/index.tsx",
      "type": "registry:ui",
      "target": "components/jetbrains-ui/icons/plugins/bdt/chart-pie/index.tsx",
      "content": "import React from 'react';\nimport { cn } from '@/lib/utils';\nimport { type IconProps, type SvgProps, sizeMap } from '../../types';\n\nexport type ChartPieProps = IconProps;\n\nconst ChartPieLight: React.FC<SvgProps> = ({\n  size,\n  className,\n  title,\n  role,\n  'aria-label': ariaLabel,\n  'aria-hidden': ariaHidden,\n}) => (\n  <svg\n    width={size}\n    height={size}\n    viewBox=\"0 0 16 16\"\n    fill=\"none\"\n    xmlns=\"http://www.w3.org/2000/svg\"\n    className={className}\n    role={role}\n    aria-label={ariaLabel}\n    aria-hidden={ariaHidden}\n  >\n    {title && <title>{title}</title>}\n    <path\n      d=\"M7.5 8.5h5.977A5.5 5.5 0 1 1 7.5 2.523z\"\n      fill=\"#EBECF0\"\n      stroke=\"#6C707E\"\n    />\n    <path\n      d=\"M9.5 1.523A5.5 5.5 0 0 1 14.477 6.5H9.5z\"\n      fill=\"#EDF3FF\"\n      stroke=\"#3574F0\"\n    />\n  </svg>\n);\n\nconst ChartPieDark: React.FC<SvgProps> = ({\n  size,\n  className,\n  title,\n  role,\n  'aria-label': ariaLabel,\n  'aria-hidden': ariaHidden,\n}) => (\n  <svg\n    width={size}\n    height={size}\n    viewBox=\"0 0 16 16\"\n    fill=\"none\"\n    xmlns=\"http://www.w3.org/2000/svg\"\n    className={className}\n    role={role}\n    aria-label={ariaLabel}\n    aria-hidden={ariaHidden}\n  >\n    {title && <title>{title}</title>}\n    <path\n      d=\"M7.5 8.5h5.977A5.5 5.5 0 1 1 7.5 2.523z\"\n      fill=\"#43454A\"\n      stroke=\"#CED0D6\"\n    />\n    <path\n      d=\"M9.5 1.523A5.5 5.5 0 0 1 14.477 6.5H9.5z\"\n      fill=\"#25324D\"\n      stroke=\"#548AF7\"\n    />\n  </svg>\n);\n\nexport const ChartPie: React.FC<ChartPieProps> = ({\n  size = 'md',\n  mode = 'light',\n  className,\n  'aria-label': ariaLabel,\n  title,\n  ...props\n}) => {\n  const SvgComponent = mode === 'light' ? ChartPieLight : ChartPieDark;\n\n  return (\n    <SvgComponent\n      size={sizeMap[size]}\n      className={cn('inline-block flex-shrink-0', className)}\n      title={title}\n      role={ariaLabel ? 'img' : 'presentation'}\n      aria-label={ariaLabel}\n      aria-hidden={!ariaLabel}\n      {...props}\n    />\n  );\n};"
    },
    {
      "path": "registry/icons/plugins/bdt/chart-scatter/index.tsx",
      "type": "registry:ui",
      "target": "components/jetbrains-ui/icons/plugins/bdt/chart-scatter/index.tsx",
      "content": "import React from 'react';\nimport { cn } from '@/lib/utils';\nimport { type IconProps, type SvgProps, sizeMap } from '../../types';\n\nexport type ChartScatterProps = IconProps;\n\nconst ChartScatterLight: React.FC<SvgProps> = ({\n  size,\n  className,\n  title,\n  role,\n  'aria-label': ariaLabel,\n  'aria-hidden': ariaHidden,\n}) => (\n  <svg\n    width={size}\n    height={size}\n    viewBox=\"0 0 16 16\"\n    fill=\"none\"\n    xmlns=\"http://www.w3.org/2000/svg\"\n    className={className}\n    role={role}\n    aria-label={ariaLabel}\n    aria-hidden={ariaHidden}\n  >\n    {title && <title>{title}</title>}\n    <path\n      d=\"M1.5 2a.5.5 0 0 1 .5.5V13h12.5a.5.5 0 0 1 0 1H2a1 1 0 0 1-1-1V2.5a.5.5 0 0 1 .5-.5\"\n      fill=\"#6C707E\"\n    />\n    <rect\n      x=\"3.5\"\n      y=\"6.5\"\n      width=\"3\"\n      height=\"3\"\n      rx=\".5\"\n      fill=\"#EDF3FF\"\n      stroke=\"#3574F0\"\n    />\n    <rect\n      x=\"8.5\"\n      y=\"2.5\"\n      width=\"3\"\n      height=\"3\"\n      rx=\".5\"\n      fill=\"#EDF3FF\"\n      stroke=\"#3574F0\"\n    />\n    <rect\n      x=\"11.5\"\n      y=\"7.5\"\n      width=\"3\"\n      height=\"3\"\n      rx=\".5\"\n      fill=\"#EDF3FF\"\n      stroke=\"#3574F0\"\n    />\n  </svg>\n);\n\nconst ChartScatterDark: React.FC<SvgProps> = ({\n  size,\n  className,\n  title,\n  role,\n  'aria-label': ariaLabel,\n  'aria-hidden': ariaHidden,\n}) => (\n  <svg\n    width={size}\n    height={size}\n    viewBox=\"0 0 16 16\"\n    fill=\"none\"\n    xmlns=\"http://www.w3.org/2000/svg\"\n    className={className}\n    role={role}\n    aria-label={ariaLabel}\n    aria-hidden={ariaHidden}\n  >\n    {title && <title>{title}</title>}\n    <path\n      d=\"M1.5 2a.5.5 0 0 1 .5.5V13h12.5a.5.5 0 0 1 0 1H2a1 1 0 0 1-1-1V2.5a.5.5 0 0 1 .5-.5\"\n      fill=\"#CED0D6\"\n    />\n    <rect\n      x=\"3.5\"\n      y=\"6.5\"\n      width=\"3\"\n      height=\"3\"\n      rx=\".5\"\n      fill=\"#25324D\"\n      stroke=\"#548AF7\"\n    />\n    <rect\n      x=\"8.5\"\n      y=\"2.5\"\n      width=\"3\"\n      height=\"3\"\n      rx=\".5\"\n      fill=\"#25324D\"\n      stroke=\"#548AF7\"\n    />\n    <rect\n      x=\"11.5\"\n      y=\"7.5\"\n      width=\"3\"\n      height=\"3\"\n      rx=\".5\"\n      fill=\"#25324D\"\n      stroke=\"#548AF7\"\n    />\n  </svg>\n);\n\nexport const ChartScatter: React.FC<ChartScatterProps> = ({\n  size = 'md',\n  mode = 'light',\n  className,\n  'aria-label': ariaLabel,\n  title,\n  ...props\n}) => {\n  const SvgComponent = mode === 'light' ? ChartScatterLight : ChartScatterDark;\n\n  return (\n    <SvgComponent\n      size={sizeMap[size]}\n      className={cn('inline-block flex-shrink-0', className)}\n      title={title}\n      role={ariaLabel ? 'img' : 'presentation'}\n      aria-label={ariaLabel}\n      aria-hidden={!ariaLabel}\n      {...props}\n    />\n  );\n};"
    },
    {
      "path": "registry/icons/plugins/bdt/chart-stock/index.tsx",
      "type": "registry:ui",
      "target": "components/jetbrains-ui/icons/plugins/bdt/chart-stock/index.tsx",
      "content": "import React from 'react';\nimport { cn } from '@/lib/utils';\nimport { type IconProps, type SvgProps, sizeMap } from '../../types';\n\nexport type ChartStockProps = IconProps;\n\nconst ChartStockLight: React.FC<SvgProps> = ({\n  size,\n  className,\n  title,\n  role,\n  'aria-label': ariaLabel,\n  'aria-hidden': ariaHidden,\n}) => (\n  <svg\n    width={size}\n    height={size}\n    viewBox=\"0 0 16 16\"\n    fill=\"none\"\n    xmlns=\"http://www.w3.org/2000/svg\"\n    className={className}\n    role={role}\n    aria-label={ariaLabel}\n    aria-hidden={ariaHidden}\n  >\n    {title && <title>{title}</title>}\n    <path\n      d=\"M1.5 2a.5.5 0 0 1 .5.5V13h12.5a.5.5 0 0 1 0 1H2a1 1 0 0 1-1-1V2.5a.5.5 0 0 1 .5-.5\"\n      fill=\"#6C707E\"\n    />\n    <path\n      fillRule=\"evenodd\"\n      clipRule=\"evenodd\"\n      d=\"M8 2a1 1 0 0 0-1 1v4a1 1 0 0 0 1 1h1a1 1 0 0 0 1-1V3a1 1 0 0 0-1-1zm0 1h1v4H8zM3 5a1 1 0 0 1 1-1h1a1 1 0 0 1 1 1v5a1 1 0 0 1-1 1H4a1 1 0 0 1-1-1zm2 0H4v5h1zM11 5a1 1 0 0 1 1-1h1a1 1 0 0 1 1 1v6a1 1 0 0 1-1 1h-1a1 1 0 0 1-1-1zm2 0h-1v6h1z\"\n      fill=\"#3574F0\"\n    />\n    <path d=\"M8 3h1v4H8zM5 5H4v5h1zM12 5h1v6h-1z\" fill=\"#EDF3FF\" />\n  </svg>\n);\n\nconst ChartStockDark: React.FC<SvgProps> = ({\n  size,\n  className,\n  title,\n  role,\n  'aria-label': ariaLabel,\n  'aria-hidden': ariaHidden,\n}) => (\n  <svg\n    width={size}\n    height={size}\n    viewBox=\"0 0 16 16\"\n    fill=\"none\"\n    xmlns=\"http://www.w3.org/2000/svg\"\n    className={className}\n    role={role}\n    aria-label={ariaLabel}\n    aria-hidden={ariaHidden}\n  >\n    {title && <title>{title}</title>}\n    <path\n      d=\"M1.5 2a.5.5 0 0 1 .5.5V13h12.5a.5.5 0 0 1 0 1H2a1 1 0 0 1-1-1V2.5a.5.5 0 0 1 .5-.5\"\n      fill=\"#CED0D6\"\n    />\n    <path\n      fillRule=\"evenodd\"\n      clipRule=\"evenodd\"\n      d=\"M8 2a1 1 0 0 0-1 1v4a1 1 0 0 0 1 1h1a1 1 0 0 0 1-1V3a1 1 0 0 0-1-1zm0 1h1v4H8zM3 5a1 1 0 0 1 1-1h1a1 1 0 0 1 1 1v5a1 1 0 0 1-1 1H4a1 1 0 0 1-1-1zm2 0H4v5h1zM11 5a1 1 0 0 1 1-1h1a1 1 0 0 1 1 1v6a1 1 0 0 1-1 1h-1a1 1 0 0 1-1-1zm2 0h-1v6h1z\"\n      fill=\"#548AF7\"\n    />\n    <path d=\"M8 3h1v4H8zM5 5H4v5h1zM12 5h1v6h-1z\" fill=\"#25324D\" />\n  </svg>\n);\n\nexport const ChartStock: React.FC<ChartStockProps> = ({\n  size = 'md',\n  mode = 'light',\n  className,\n  'aria-label': ariaLabel,\n  title,\n  ...props\n}) => {\n  const SvgComponent = mode === 'light' ? ChartStockLight : ChartStockDark;\n\n  return (\n    <SvgComponent\n      size={sizeMap[size]}\n      className={cn('inline-block flex-shrink-0', className)}\n      title={title}\n      role={ariaLabel ? 'img' : 'presentation'}\n      aria-label={ariaLabel}\n      aria-hidden={!ariaLabel}\n      {...props}\n    />\n  );\n};"
    },
    {
      "path": "registry/icons/plugins/bdt/cluster/index.tsx",
      "type": "registry:ui",
      "target": "components/jetbrains-ui/icons/plugins/bdt/cluster/index.tsx",
      "content": "import React from 'react';\nimport { cn } from '@/lib/utils';\nimport { type IconProps, type SvgProps, sizeMap } from '../../types';\n\nexport type ClusterProps = IconProps;\n\nconst ClusterLight: React.FC<SvgProps> = ({\n  size,\n  className,\n  title,\n  role,\n  'aria-label': ariaLabel,\n  'aria-hidden': ariaHidden,\n}) => (\n  <svg\n    width={size}\n    height={size}\n    viewBox=\"0 0 16 16\"\n    fill=\"none\"\n    xmlns=\"http://www.w3.org/2000/svg\"\n    className={className}\n    role={role}\n    aria-label={ariaLabel}\n    aria-hidden={ariaHidden}\n  >\n    {title && <title>{title}</title>}\n    <path\n      d=\"M9 3a1 1 0 1 1-2 0 1 1 0 0 1 2 0M3 7.5a1 1 0 1 0 0-2 1 1 0 0 0 0 2M13 7.5a1 1 0 1 0 0-2 1 1 0 0 0 0 2M5 13a1 1 0 1 0 0-2 1 1 0 0 0 0 2M12 12a1 1 0 1 1-2 0 1 1 0 0 1 2 0\"\n      fill=\"#EBECF0\"\n    />\n    <path\n      fillRule=\"evenodd\"\n      clipRule=\"evenodd\"\n      d=\"M9.874 3.701a2 2 0 1 0-3.747 0L4.3 4.98A2 2 0 1 0 3.192 8.49l.676 1.86a2 2 0 1 0 3.069 2.15h2.126a2 2 0 1 0 3.069-2.15l.676-1.86q.095.009.192.009a2 2 0 1 0-1.3-3.52zm-.574.82C8.95 4.818 8.496 5 8 5s-.95-.18-1.3-.48L4.874 5.8a1.998 1.998 0 0 1-.742 2.35l.676 1.86A2 2 0 0 1 6.937 11.5h2.126a2 2 0 0 1 2.129-1.49l.676-1.86a2 2 0 0 1-.742-2.351zm-.304-1.434Q9 3.043 9 3a1 1 0 1 0-.004.087m1.83 7.928A.998.998 0 0 1 12 12a1 1 0 1 1-1.174-.985m-4.96.485a1 1 0 0 1 0 1 .999.999 0 1 1 0-1m-2.1-4.357A1 1 0 0 1 3 7.5a1 1 0 1 1 .766-.357M13 7.5a1 1 0 1 0 0-2 1 1 0 0 0 0 2\"\n      fill=\"#6C707E\"\n    />\n  </svg>\n);\n\nconst ClusterDark: React.FC<SvgProps> = ({\n  size,\n  className,\n  title,\n  role,\n  'aria-label': ariaLabel,\n  'aria-hidden': ariaHidden,\n}) => (\n  <svg\n    width={size}\n    height={size}\n    viewBox=\"0 0 16 16\"\n    fill=\"none\"\n    xmlns=\"http://www.w3.org/2000/svg\"\n    className={className}\n    role={role}\n    aria-label={ariaLabel}\n    aria-hidden={ariaHidden}\n  >\n    {title && <title>{title}</title>}\n    <path\n      d=\"M9 3a1 1 0 1 1-2 0 1 1 0 0 1 2 0M3 7.5a1 1 0 1 0 0-2 1 1 0 0 0 0 2M13 7.5a1 1 0 1 0 0-2 1 1 0 0 0 0 2M5 13a1 1 0 1 0 0-2 1 1 0 0 0 0 2M12 12a1 1 0 1 1-2 0 1 1 0 0 1 2 0\"\n      fill=\"#43454A\"\n    />\n    <path\n      fillRule=\"evenodd\"\n      clipRule=\"evenodd\"\n      d=\"M9.874 3.701a2 2 0 1 0-3.747 0L4.3 4.98A2 2 0 1 0 3.192 8.49l.676 1.86a2 2 0 1 0 3.069 2.15h2.126a2 2 0 1 0 3.069-2.15l.676-1.86q.095.009.192.009a2 2 0 1 0-1.3-3.52zm-.574.82C8.95 4.818 8.496 5 8 5s-.95-.18-1.3-.48L4.874 5.8a1.998 1.998 0 0 1-.742 2.35l.676 1.86A2 2 0 0 1 6.937 11.5h2.126a2 2 0 0 1 2.129-1.49l.676-1.86a2 2 0 0 1-.742-2.351zm-.304-1.434Q9 3.043 9 3a1 1 0 1 0-.004.087m1.83 7.928A.998.998 0 0 1 12 12a1 1 0 1 1-1.174-.985m-4.96.485a1 1 0 0 1 0 1 .999.999 0 1 1 0-1m-2.1-4.357A1 1 0 0 1 3 7.5a1 1 0 1 1 .766-.357M13 7.5a1 1 0 1 0 0-2 1 1 0 0 0 0 2\"\n      fill=\"#CED0D6\"\n    />\n  </svg>\n);\n\nexport const Cluster: React.FC<ClusterProps> = ({\n  size = 'md',\n  mode = 'light',\n  className,\n  'aria-label': ariaLabel,\n  title,\n  ...props\n}) => {\n  const SvgComponent = mode === 'light' ? ClusterLight : ClusterDark;\n\n  return (\n    <SvgComponent\n      size={sizeMap[size]}\n      className={cn('inline-block flex-shrink-0', className)}\n      title={title}\n      role={ariaLabel ? 'img' : 'presentation'}\n      aria-label={ariaLabel}\n      aria-hidden={!ariaLabel}\n      {...props}\n    />\n  );\n};"
    },
    {
      "path": "registry/icons/plugins/bdt/dbt-utility/index.tsx",
      "type": "registry:ui",
      "target": "components/jetbrains-ui/icons/plugins/bdt/dbt-utility/index.tsx",
      "content": "import React from 'react';\nimport { cn } from '@/lib/utils';\nimport { type IconProps, type SvgProps, sizeMap } from '../../types';\n\nexport type DbtUtilityProps = IconProps;\n\nconst DbtUtilityLight: React.FC<SvgProps> = ({\n  size,\n  className,\n  title,\n  role,\n  'aria-label': ariaLabel,\n  'aria-hidden': ariaHidden,\n}) => (\n  <svg\n    width={size}\n    height={size}\n    viewBox=\"0 0 16 16\"\n    fill=\"none\"\n    xmlns=\"http://www.w3.org/2000/svg\"\n    className={className}\n    role={role}\n    aria-label={ariaLabel}\n    aria-hidden={ariaHidden}\n  >\n    {title && <title>{title}</title>}\n    <path\n      d=\"M14.405 1.582c.33.317.544.734.595 1.19 0 .19-.05.317-.165.557-.114.24-1.519 2.671-1.936 3.342a2.55 2.55 0 0 0 0 2.633c.418.67 1.823 3.114 1.936 3.354.114.24.165.355.165.545-.05.455-.253.873-.582 1.177-.317.329-.734.544-1.177.582-.19 0-.317-.05-.545-.165-.228-.114-2.709-1.48-3.38-1.898-.05-.026-.1-.064-.164-.089l-3.317-1.962a2.82 2.82 0 0 0 .81 1.684c.09.088.178.164.28.24-.077.038-.166.076-.241.127-.671.418-3.114 1.823-3.355 1.936-.24.114-.354.165-.557.165a1.87 1.87 0 0 1-1.177-.582A1.95 1.95 0 0 1 1 13.228c.013-.19.063-.38.165-.544C1.278 12.443 2.684 10 3.1 9.329c.24-.392.367-.848.367-1.316s-.126-.924-.367-1.317C2.684 6 1.266 3.557 1.165 3.316A1.2 1.2 0 0 1 1 2.772c.05-.456.253-.873.582-1.19.317-.329.734-.531 1.19-.582.19.013.38.063.557.165.203.088 1.987 1.126 2.937 1.683l.215.127q.114.075.19.114l.101.063 3.38 2a2.79 2.79 0 0 0-1.076-1.924c.076-.038.165-.076.24-.127.671-.417 3.114-1.835 3.355-1.936.164-.102.354-.152.557-.165.443.05.86.253 1.177.582M8.177 8.9l.722-.722a.245.245 0 0 0 0-.354L8.177 7.1a.245.245 0 0 0-.354 0l-.722.722a.245.245 0 0 0 0 .354l.722.722c.088.088.253.088.354 0\"\n      fill=\"#E66D17\"\n    />\n  </svg>\n);\n\nconst DbtUtilityDark: React.FC<SvgProps> = ({\n  size,\n  className,\n  title,\n  role,\n  'aria-label': ariaLabel,\n  'aria-hidden': ariaHidden,\n}) => (\n  <svg\n    width={size}\n    height={size}\n    viewBox=\"0 0 16 16\"\n    fill=\"none\"\n    xmlns=\"http://www.w3.org/2000/svg\"\n    className={className}\n    role={role}\n    aria-label={ariaLabel}\n    aria-hidden={ariaHidden}\n  >\n    {title && <title>{title}</title>}\n    <path\n      d=\"M14.405 1.582c.33.317.544.734.595 1.19 0 .19-.05.317-.165.557-.114.24-1.519 2.671-1.936 3.342a2.55 2.55 0 0 0 0 2.633c.418.67 1.823 3.114 1.936 3.354.114.24.165.355.165.545-.05.455-.253.873-.582 1.177-.317.329-.734.544-1.177.582-.19 0-.317-.05-.545-.165-.228-.114-2.709-1.48-3.38-1.898-.05-.026-.1-.064-.164-.089l-3.317-1.962a2.82 2.82 0 0 0 .81 1.684c.09.088.178.164.28.24-.077.038-.166.076-.241.127-.671.418-3.114 1.823-3.355 1.936-.24.114-.354.165-.557.165a1.87 1.87 0 0 1-1.177-.582A1.95 1.95 0 0 1 1 13.228c.013-.19.063-.38.165-.544C1.278 12.443 2.684 10 3.1 9.329c.24-.392.367-.848.367-1.316s-.126-.924-.367-1.317C2.684 6 1.266 3.557 1.165 3.316A1.2 1.2 0 0 1 1 2.772c.05-.456.253-.873.582-1.19.317-.329.734-.531 1.19-.582.19.013.38.063.557.165.203.088 1.987 1.126 2.937 1.683l.215.127q.114.075.19.114l.101.063 3.38 2a2.79 2.79 0 0 0-1.076-1.924c.076-.038.165-.076.24-.127.671-.417 3.114-1.835 3.355-1.936.164-.102.354-.152.557-.165.443.05.86.253 1.177.582M8.177 8.9l.722-.722a.245.245 0 0 0 0-.354L8.177 7.1a.245.245 0 0 0-.354 0l-.722.722a.245.245 0 0 0 0 .354l.722.722c.088.088.253.088.354 0\"\n      fill=\"#C77D55\"\n    />\n  </svg>\n);\n\nexport const DbtUtility: React.FC<DbtUtilityProps> = ({\n  size = 'md',\n  mode = 'light',\n  className,\n  'aria-label': ariaLabel,\n  title,\n  ...props\n}) => {\n  const SvgComponent = mode === 'light' ? DbtUtilityLight : DbtUtilityDark;\n\n  return (\n    <SvgComponent\n      size={sizeMap[size]}\n      className={cn('inline-block flex-shrink-0', className)}\n      title={title}\n      role={ariaLabel ? 'img' : 'presentation'}\n      aria-label={ariaLabel}\n      aria-hidden={!ariaLabel}\n      {...props}\n    />\n  );\n};"
    },
    {
      "path": "registry/icons/plugins/bdt/flink/index.tsx",
      "type": "registry:ui",
      "target": "components/jetbrains-ui/icons/plugins/bdt/flink/index.tsx",
      "content": "import React from 'react';\nimport { cn } from '@/lib/utils';\nimport { type IconProps, type SvgProps, sizeMap } from '../../types';\n\nexport type FlinkProps = IconProps;\n\nconst FlinkLight: React.FC<SvgProps> = ({\n  size,\n  className,\n  title,\n  role,\n  'aria-label': ariaLabel,\n  'aria-hidden': ariaHidden,\n}) => (\n  <svg\n    width={size}\n    height={size}\n    viewBox=\"0 0 16 16\"\n    fill=\"none\"\n    xmlns=\"http://www.w3.org/2000/svg\"\n    className={className}\n    role={role}\n    aria-label={ariaLabel}\n    aria-hidden={ariaHidden}\n  >\n    {title && <title>{title}</title>}\n    <path fill=\"#FEAB6C\" d=\"M5 2H6V3H5z\" />\n    <path fill=\"#F9D88C\" d=\"M6 2H7V3H6z\" />\n    <path fill=\"#FE9E52\" d=\"M7 2H8V3H7z\" />\n    <path fill=\"#F9D88C\" d=\"M8 2H9V3H8z\" />\n    <path fill=\"#F9DD9D\" d=\"M6 3H7V4H6z\" />\n    <path fill=\"#FE9F52\" d=\"M7 3H8V4H7z\" />\n    <path fill=\"#F9D88C\" d=\"M8 3H9V4H8z\" />\n    <path fill=\"#F9D88C\" d=\"M9 3H10V4H9z\" />\n    <path fill=\"#FB5F81\" d=\"M5 4H6V5H5z\" />\n    <path fill=\"#F57C7C\" d=\"M6 4H7V5H6z\" />\n    <path fill=\"#FE9E52\" d=\"M8 4H9V5H8z\" />\n    <path fill=\"#F57C7C\" d=\"M9 4H10V5H9z\" />\n    <path fill=\"#FB5F81\" d=\"M4 5H5V6H4z\" />\n    <path fill=\"#F57B7C\" d=\"M5 5H6V6H5z\" />\n    <path fill=\"#F57B7C\" d=\"M7 5H8V6H7z\" />\n    <path fill=\"#C62E53\" d=\"M9 5H10V6H9z\" />\n    <path fill=\"#951B39\" d=\"M10 5H11V6H10z\" />\n    <path fill=\"#AE72B2\" d=\"M3 6H4V7H3z\" />\n    <path fill=\"#F57B7C\" d=\"M6 6H7V7H6z\" />\n    <path fill=\"#F57C7B\" d=\"M8 6H9V7H8z\" />\n    <path fill=\"#C54D5B\" d=\"M9 6H10V7H9z\" />\n    <path fill=\"#951B39\" d=\"M1 7H2V8H1z\" />\n    <path fill=\"#AE72B2\" d=\"M4 7H5V8H4z\" />\n    <path fill=\"#AE72B2\" d=\"M6 7H7V8H6z\" />\n    <path fill=\"#C54D5B\" d=\"M7 7H8V8H7z\" />\n    <path fill=\"#C62E53\" d=\"M8 7H9V8H8z\" />\n    <path fill=\"#B92D4E\" d=\"M12 7H13V8H12z\" />\n    <path fill=\"#A058A3\" d=\"M5 8H6V9H5z\" />\n    <path fill=\"#C62E53\" d=\"M6 8H7V9H6z\" />\n    <path fill=\"#9A3D70\" d=\"M7 8H8V9H7z\" />\n    <path d=\"M7 4h1v1H7z\" fill=\"#F8416D\" />\n    <path\n      fillRule=\"evenodd\"\n      clipRule=\"evenodd\"\n      d=\"M7 6V5H6v1H4v1H3v1H2v1h1v1h1V9h1V8h1V6zM4 8V7h1v1zm0 0v1H3V8z\"\n      fill=\"#F8416D\"\n    />\n    <path d=\"M8 6v1H7V6zM8 6h1V5H8z\" fill=\"#F8416D\" />\n    <path fill=\"#9A3D70\" d=\"M4 9H5V10H4z\" />\n    <path fill=\"#9A3D70\" d=\"M5 9H6V10H5z\" />\n    <path fill=\"#951B39\" d=\"M11 9H12V10H11z\" />\n    <path fill=\"#9A3D70\" d=\"M4 10H5V11H4z\" />\n    <path fill=\"#961B39\" d=\"M8 11H9V12H8z\" />\n    <path fill=\"#C62E53\" d=\"M10 11H11V12H10z\" />\n    <path fill=\"#951B39\" d=\"M12 11H13V12H12z\" />\n    <path fill=\"#951B39\" d=\"M1 12H2V13H1z\" />\n    <path d=\"M3 7H2v1h1v1H2v3h1v1h1v-3H3V9h1V8H3z\" fill=\"#A05AA5\" />\n    <path fill=\"#961B39\" d=\"M8 12H9V13H8z\" />\n    <path fill=\"#CC5F00\" d=\"M11 12H12V13H11z\" />\n    <path fill=\"#FE9C00\" d=\"M12 12H13V13H12z\" />\n    <path fill=\"#951B39\" d=\"M13 12H14V13H13z\" />\n    <path fill=\"#961B39\" d=\"M10 13H11V14H10z\" />\n    <path fill=\"#C62E53\" d=\"M11 13H12V14H11z\" />\n    <path\n      d=\"M11 6h1v2h1v1h-2v1h2V9h1v2h-4v1H9v-1H8v2h2v1H3v-1h1v-2h2v-1h2V9h1V8h1V7h1zM3 13H2v-1h1zM13 13h-1v1h1z\"\n      fill=\"#F8416C\"\n    />\n    <path fill=\"#961B39\" d=\"M3 14H4V15H3z\" />\n    <path\n      d=\"M9 1H5v1H4v1h1v1H4v1H3v1H2v1h1V6h1V5h1V4h1V3H5V2h4v1h1v2h1v1h-1v1H9v1H8v1H6v1H5v1h1v-1h2V9h1V8h1V7h1V6h1v1h1V6h-1V5h-1V3h-1V2H9zM2 8H1v4h1zM14 8h-1v1h-1v1h1V9h1v2h-1v1h1v-1h1V9h-1zM12 11h-1v1H9v1h2v-1h1zM3 13H2v1h1zM13 13h1v1h-1zM13 15v-1H4v1z\"\n      fill=\"#392A31\"\n    />\n  </svg>\n);\n\nconst FlinkDark: React.FC<SvgProps> = ({\n  size,\n  className,\n  title,\n  role,\n  'aria-label': ariaLabel,\n  'aria-hidden': ariaHidden,\n}) => (\n  <svg\n    width={size}\n    height={size}\n    viewBox=\"0 0 16 16\"\n    fill=\"none\"\n    xmlns=\"http://www.w3.org/2000/svg\"\n    className={className}\n    role={role}\n    aria-label={ariaLabel}\n    aria-hidden={ariaHidden}\n  >\n    {title && <title>{title}</title>}\n    <path fill=\"#FEAB6C\" d=\"M5 2H6V3H5z\" />\n    <path fill=\"#F9D88C\" d=\"M6 2H7V3H6z\" />\n    <path fill=\"#FE9E52\" d=\"M7 2H8V3H7z\" />\n    <path fill=\"#F9D88C\" d=\"M8 2H9V3H8z\" />\n    <path fill=\"#F9DD9D\" d=\"M6 3H7V4H6z\" />\n    <path fill=\"#FE9F52\" d=\"M7 3H8V4H7z\" />\n    <path fill=\"#F9D88C\" d=\"M8 3H9V4H8z\" />\n    <path fill=\"#F9D88C\" d=\"M9 3H10V4H9z\" />\n    <path fill=\"#FB5F81\" d=\"M5 4H6V5H5z\" />\n    <path fill=\"#F57C7C\" d=\"M6 4H7V5H6z\" />\n    <path fill=\"#FE9E52\" d=\"M8 4H9V5H8z\" />\n    <path fill=\"#F57C7C\" d=\"M9 4H10V5H9z\" />\n    <path fill=\"#FB5F81\" d=\"M4 5H5V6H4z\" />\n    <path fill=\"#F57B7C\" d=\"M5 5H6V6H5z\" />\n    <path fill=\"#F57B7C\" d=\"M7 5H8V6H7z\" />\n    <path fill=\"#C62E53\" d=\"M9 5H10V6H9z\" />\n    <path fill=\"#951B39\" d=\"M10 5H11V6H10z\" />\n    <path fill=\"#AE72B2\" d=\"M3 6H4V7H3z\" />\n    <path fill=\"#F57B7C\" d=\"M6 6H7V7H6z\" />\n    <path fill=\"#F57C7B\" d=\"M8 6H9V7H8z\" />\n    <path fill=\"#C54D5B\" d=\"M9 6H10V7H9z\" />\n    <path fill=\"#951B39\" d=\"M1 7H2V8H1z\" />\n    <path fill=\"#AE72B2\" d=\"M4 7H5V8H4z\" />\n    <path fill=\"#AE72B2\" d=\"M6 7H7V8H6z\" />\n    <path fill=\"#C54D5B\" d=\"M7 7H8V8H7z\" />\n    <path fill=\"#C62E53\" d=\"M8 7H9V8H8z\" />\n    <path fill=\"#B92D4E\" d=\"M12 7H13V8H12z\" />\n    <path fill=\"#A058A3\" d=\"M5 8H6V9H5z\" />\n    <path fill=\"#C62E53\" d=\"M6 8H7V9H6z\" />\n    <path fill=\"#9A3D70\" d=\"M7 8H8V9H7z\" />\n    <path d=\"M7 4h1v1H7z\" fill=\"#F8416D\" />\n    <path\n      fillRule=\"evenodd\"\n      clipRule=\"evenodd\"\n      d=\"M7 6V5H6v1H4v1H3v1H2v1h1v1h1V9h1V8h1V6zM4 8V7h1v1zm0 0v1H3V8z\"\n      fill=\"#F8416D\"\n    />\n    <path d=\"M8 6v1H7V6zM8 6h1V5H8z\" fill=\"#F8416D\" />\n    <path fill=\"#9A3D70\" d=\"M4 9H5V10H4z\" />\n    <path fill=\"#9A3D70\" d=\"M5 9H6V10H5z\" />\n    <path fill=\"#951B39\" d=\"M11 9H12V10H11z\" />\n    <path fill=\"#9A3D70\" d=\"M4 10H5V11H4z\" />\n    <path fill=\"#961B39\" d=\"M8 11H9V12H8z\" />\n    <path fill=\"#C62E53\" d=\"M10 11H11V12H10z\" />\n    <path fill=\"#951B39\" d=\"M12 11H13V12H12z\" />\n    <path fill=\"#951B39\" d=\"M1 12H2V13H1z\" />\n    <path d=\"M3 7H2v1h1v1H2v3h1v1h1v-3H3V9h1V8H3z\" fill=\"#A05AA5\" />\n    <path fill=\"#961B39\" d=\"M8 12H9V13H8z\" />\n    <path fill=\"#CC5F00\" d=\"M11 12H12V13H11z\" />\n    <path fill=\"#FE9C00\" d=\"M12 12H13V13H12z\" />\n    <path fill=\"#951B39\" d=\"M13 12H14V13H13z\" />\n    <path fill=\"#961B39\" d=\"M10 13H11V14H10z\" />\n    <path fill=\"#C62E53\" d=\"M11 13H12V14H11z\" />\n    <path\n      d=\"M11 6h1v2h1v1h-2v1h2V9h1v2h-4v1H9v-1H8v2h2v1H3v-1h1v-2h2v-1h2V9h1V8h1V7h1zM3 13H2v-1h1zM13 13h-1v1h1z\"\n      fill=\"#F8416C\"\n    />\n    <path fill=\"#961B39\" d=\"M3 14H4V15H3z\" />\n    <path\n      d=\"M9 1H5v1H4v1h1v1H4v1H3v1H2v1h1V6h1V5h1V4h1V3H5V2h4v1h1v2h1v1h-1v1H9v1H8v1H6v1H5v1h1v-1h2V9h1V8h1V7h1V6h1v1h1V6h-1V5h-1V3h-1V2H9zM2 8H1v4h1zM14 8h-1v1h-1v1h1V9h1v2h-1v1h1v-1h1V9h-1zM12 11h-1v1H9v1h2v-1h1zM3 13H2v1h1zM13 13h1v1h-1zM13 15v-1H4v1z\"\n      fill=\"#392A31\"\n    />\n  </svg>\n);\n\nexport const Flink: React.FC<FlinkProps> = ({\n  size = 'md',\n  mode = 'light',\n  className,\n  'aria-label': ariaLabel,\n  title,\n  ...props\n}) => {\n  const SvgComponent = mode === 'light' ? FlinkLight : FlinkDark;\n\n  return (\n    <SvgComponent\n      size={sizeMap[size]}\n      className={cn('inline-block flex-shrink-0', className)}\n      title={title}\n      role={ariaLabel ? 'img' : 'presentation'}\n      aria-label={ariaLabel}\n      aria-hidden={!ariaLabel}\n      {...props}\n    />\n  );\n};"
    },
    {
      "path": "registry/icons/plugins/bdt/py-spark/index.tsx",
      "type": "registry:ui",
      "target": "components/jetbrains-ui/icons/plugins/bdt/py-spark/index.tsx",
      "content": "import React from 'react';\nimport { cn } from '@/lib/utils';\nimport { type IconProps, type SvgProps, sizeMap } from '../../types';\n\nexport type PySparkProps = IconProps;\n\nconst PySparkLight: React.FC<SvgProps> = ({\n  size,\n  className,\n  title,\n  role,\n  'aria-label': ariaLabel,\n  'aria-hidden': ariaHidden,\n}) => (\n  <svg\n    width={size}\n    height={size}\n    viewBox=\"0 0 16 16\"\n    fill=\"none\"\n    xmlns=\"http://www.w3.org/2000/svg\"\n    className={className}\n    role={role}\n    aria-label={ariaLabel}\n    aria-hidden={ariaHidden}\n  >\n    {title && <title>{title}</title>}\n    <path\n      fillRule=\"evenodd\"\n      clipRule=\"evenodd\"\n      d=\"M14 11.5V11h1a1 1 0 0 1 1 1v1a1 1 0 0 1-1 1h-1v1a1 1 0 0 1-1 1h-1a1 1 0 0 1-1-1v-1.5a1 1 0 0 1 1-1h1a1 1 0 0 0 1-1M12.5 15a.5.5 0 1 0 0-1 .5.5 0 0 0 0 1\"\n      fill=\"#FFAF0F\"\n    />\n    <path\n      fillRule=\"evenodd\"\n      clipRule=\"evenodd\"\n      d=\"M11 13.5v.5h-1a1 1 0 0 1-1-1v-1a1 1 0 0 1 1-1h1v-1a1 1 0 0 1 1-1h1a1 1 0 0 1 1 1v1.5a1 1 0 0 1-1 1h-1a1 1 0 0 0-1 1m1.5-2.5a.5.5 0 1 0 0-1 .5.5 0 0 0 0 1\"\n      fill=\"#4682FA\"\n    />\n    <path\n      d=\"m1.45 8.84 3.795 1.607.813 4.01a.7.7 0 0 0 1.209.327L8 13.961v-2.483l-.683.792-.662-3.033-2.919-1.168L6.47 6.495l.244-3.099 2.35 2.06 3.071-.746-1.28 2.848.278.442h1.794l-.232-.366 1.727-3.695a.7.7 0 0 0-.786-.98l-4.047.9L6.52 1.18a.7.7 0 0 0-1.157.46l-.379 3.957-3.599 1.985a.7.7 0 0 0 .065 1.257\"\n      fill=\"#E25A1C\"\n    />\n  </svg>\n);\n\nconst PySparkDark: React.FC<SvgProps> = ({\n  size,\n  className,\n  title,\n  role,\n  'aria-label': ariaLabel,\n  'aria-hidden': ariaHidden,\n}) => (\n  <svg\n    width={size}\n    height={size}\n    viewBox=\"0 0 16 16\"\n    fill=\"none\"\n    xmlns=\"http://www.w3.org/2000/svg\"\n    className={className}\n    role={role}\n    aria-label={ariaLabel}\n    aria-hidden={ariaHidden}\n  >\n    {title && <title>{title}</title>}\n    <path\n      fillRule=\"evenodd\"\n      clipRule=\"evenodd\"\n      d=\"M14 11.5V11h1a1 1 0 0 1 1 1v1a1 1 0 0 1-1 1h-1v1a1 1 0 0 1-1 1h-1a1 1 0 0 1-1-1v-1.5a1 1 0 0 1 1-1h1a1 1 0 0 0 1-1M12.5 15a.5.5 0 1 0 0-1 .5.5 0 0 0 0 1\"\n      fill=\"#F2C55C\"\n    />\n    <path\n      fillRule=\"evenodd\"\n      clipRule=\"evenodd\"\n      d=\"M11 13.5v.5h-1a1 1 0 0 1-1-1v-1a1 1 0 0 1 1-1h1v-1a1 1 0 0 1 1-1h1a1 1 0 0 1 1 1v1.5a1 1 0 0 1-1 1h-1a1 1 0 0 0-1 1m1.5-2.5a.5.5 0 1 0 0-1 .5.5 0 0 0 0 1\"\n      fill=\"#548AF7\"\n    />\n    <path\n      d=\"m1.45 8.84 3.795 1.607.813 4.01a.7.7 0 0 0 1.209.327L8 13.961v-2.483l-.683.792-.662-3.033-2.919-1.168L6.47 6.495l.244-3.099 2.35 2.06 3.071-.746-1.28 2.848.278.442h1.794l-.232-.366 1.727-3.695a.7.7 0 0 0-.786-.98l-4.047.9L6.52 1.18a.7.7 0 0 0-1.157.46l-.379 3.957-3.599 1.985a.7.7 0 0 0 .065 1.257\"\n      fill=\"#E25A1C\"\n    />\n  </svg>\n);\n\nexport const PySpark: React.FC<PySparkProps> = ({\n  size = 'md',\n  mode = 'light',\n  className,\n  'aria-label': ariaLabel,\n  title,\n  ...props\n}) => {\n  const SvgComponent = mode === 'light' ? PySparkLight : PySparkDark;\n\n  return (\n    <SvgComponent\n      size={sizeMap[size]}\n      className={cn('inline-block flex-shrink-0', className)}\n      title={title}\n      role={ariaLabel ? 'img' : 'presentation'}\n      aria-label={ariaLabel}\n      aria-hidden={!ariaLabel}\n      {...props}\n    />\n  );\n};"
    },
    {
      "path": "registry/icons/plugins/bdt/remote-file-systems/index.tsx",
      "type": "registry:ui",
      "target": "components/jetbrains-ui/icons/plugins/bdt/remote-file-systems/index.tsx",
      "content": "import React from 'react';\nimport { cn } from '@/lib/utils';\nimport { type IconProps, type SvgProps, sizeMap } from '../../types';\n\nexport type RemoteFileSystemsProps = IconProps;\n\nconst RemoteFileSystemsLight: React.FC<SvgProps> = ({\n  size,\n  className,\n  title,\n  role,\n  'aria-label': ariaLabel,\n  'aria-hidden': ariaHidden,\n}) => (\n  <svg\n    width={size}\n    height={size}\n    viewBox=\"0 0 16 16\"\n    fill=\"none\"\n    xmlns=\"http://www.w3.org/2000/svg\"\n    className={className}\n    role={role}\n    aria-label={ariaLabel}\n    aria-hidden={ariaHidden}\n  >\n    {title && <title>{title}</title>}\n    <path\n      d=\"M8.5 13v2.5m0 0h4m-4 0h-5\"\n      stroke=\"#6C707E\"\n      strokeLinecap=\"round\"\n    />\n    <path\n      d=\"M6.414 1.586 3.586 4.414A2 2 0 0 0 3 5.828V11a2 2 0 0 0 2 2h6a2 2 0 0 0 2-2V3a2 2 0 0 0-2-2H7.828a2 2 0 0 0-1.414.586\"\n      fill=\"#EBECF0\"\n    />\n    <path\n      d=\"M7.828 1.5H11A1.5 1.5 0 0 1 12.5 3v8a1.5 1.5 0 0 1-1.5 1.5H5A1.5 1.5 0 0 1 3.5 11V5.828c0-.398.158-.78.44-1.06l2.828-2.829a1.5 1.5 0 0 1 .912-.431z\"\n      stroke=\"#6C707E\"\n    />\n  </svg>\n);\n\nconst RemoteFileSystemsDark: React.FC<SvgProps> = ({\n  size,\n  className,\n  title,\n  role,\n  'aria-label': ariaLabel,\n  'aria-hidden': ariaHidden,\n}) => (\n  <svg\n    width={size}\n    height={size}\n    viewBox=\"0 0 16 16\"\n    fill=\"none\"\n    xmlns=\"http://www.w3.org/2000/svg\"\n    className={className}\n    role={role}\n    aria-label={ariaLabel}\n    aria-hidden={ariaHidden}\n  >\n    {title && <title>{title}</title>}\n    <path\n      d=\"M8.5 13v2.5m0 0h4m-4 0h-5\"\n      stroke=\"#CED0D6\"\n      strokeLinecap=\"round\"\n    />\n    <path\n      d=\"M6.414 1.586 3.586 4.414A2 2 0 0 0 3 5.828V11a2 2 0 0 0 2 2h6a2 2 0 0 0 2-2V3a2 2 0 0 0-2-2H7.828a2 2 0 0 0-1.414.586\"\n      fill=\"#43454A\"\n    />\n    <path\n      d=\"M7.828 1.5H11A1.5 1.5 0 0 1 12.5 3v8a1.5 1.5 0 0 1-1.5 1.5H5A1.5 1.5 0 0 1 3.5 11V5.828c0-.398.158-.78.44-1.06l2.828-2.829a1.5 1.5 0 0 1 .912-.431z\"\n      stroke=\"#CED0D6\"\n    />\n  </svg>\n);\n\nexport const RemoteFileSystems: React.FC<RemoteFileSystemsProps> = ({\n  size = 'md',\n  mode = 'light',\n  className,\n  'aria-label': ariaLabel,\n  title,\n  ...props\n}) => {\n  const SvgComponent =\n    mode === 'light' ? RemoteFileSystemsLight : RemoteFileSystemsDark;\n\n  return (\n    <SvgComponent\n      size={sizeMap[size]}\n      className={cn('inline-block flex-shrink-0', className)}\n      title={title}\n      role={ariaLabel ? 'img' : 'presentation'}\n      aria-label={ariaLabel}\n      aria-hidden={!ariaLabel}\n      {...props}\n    />\n  );\n};"
    },
    {
      "path": "registry/icons/plugins/bdt/spark-run/index.tsx",
      "type": "registry:ui",
      "target": "components/jetbrains-ui/icons/plugins/bdt/spark-run/index.tsx",
      "content": "import React from 'react';\nimport { cn } from '@/lib/utils';\nimport { type IconProps, type SvgProps, sizeMap } from '../../types';\n\nexport type SparkRunProps = IconProps;\n\nconst SparkRunLight: React.FC<SvgProps> = ({\n  size,\n  className,\n  title,\n  role,\n  'aria-label': ariaLabel,\n  'aria-hidden': ariaHidden,\n}) => (\n  <svg\n    width={size}\n    height={size}\n    viewBox=\"0 0 14 14\"\n    fill=\"none\"\n    xmlns=\"http://www.w3.org/2000/svg\"\n    className={className}\n    role={role}\n    aria-label={ariaLabel}\n    aria-hidden={ariaHidden}\n  >\n    {title && <title>{title}</title>}\n    <path\n      fillRule=\"evenodd\"\n      clipRule=\"evenodd\"\n      d=\"M7 7.502A1.5 1.5 0 0 1 9.294 6.23l4.002 2.497a1.5 1.5 0 0 1 0 2.546L9.294 13.77A1.5 1.5 0 0 1 7 12.498zm1.765-.424A.5.5 0 0 0 8 7.502v4.996a.5.5 0 0 0 .765.424l4.002-2.498a.5.5 0 0 0 0-.848z\"\n      fill=\"#208A3C\"\n    />\n    <path\n      d=\"M8 7.502a.5.5 0 0 1 .765-.424l4.002 2.498a.5.5 0 0 1 0 .848l-4.002 2.498A.5.5 0 0 1 8 12.498z\"\n      fill=\"#F2FCF3\"\n    />\n    <path\n      d=\"m5.1 8.716 1.047 5.145a.702.702 0 0 1-1.107-.422l-.814-4.007L.427 7.826A.699.699 0 0 1 .362 6.57l3.603-1.983.38-3.953a.701.701 0 0 1 1.158-.46L8.574 2.85l4.052-.898a.7.7 0 0 1 .786.978l-1.698 3.631-.854-.533 1.388-2.969-3.95.876L5.284 1.31 4.91 5.208 1.388 7.146z\"\n      fill=\"#E66D17\"\n    />\n  </svg>\n);\n\nconst SparkRunDark: React.FC<SvgProps> = ({\n  size,\n  className,\n  title,\n  role,\n  'aria-label': ariaLabel,\n  'aria-hidden': ariaHidden,\n}) => (\n  <svg\n    width={size}\n    height={size}\n    viewBox=\"0 0 14 14\"\n    fill=\"none\"\n    xmlns=\"http://www.w3.org/2000/svg\"\n    className={className}\n    role={role}\n    aria-label={ariaLabel}\n    aria-hidden={ariaHidden}\n  >\n    {title && <title>{title}</title>}\n    <path\n      fillRule=\"evenodd\"\n      clipRule=\"evenodd\"\n      d=\"M7 7.502A1.5 1.5 0 0 1 9.294 6.23l4.002 2.497a1.5 1.5 0 0 1 0 2.546L9.294 13.77A1.5 1.5 0 0 1 7 12.498zm1.765-.424A.5.5 0 0 0 8 7.502v4.996a.5.5 0 0 0 .765.424l4.002-2.498a.5.5 0 0 0 0-.848z\"\n      fill=\"#57965C\"\n    />\n    <path\n      d=\"M8 7.502a.5.5 0 0 1 .765-.424l4.002 2.498a.5.5 0 0 1 0 .848l-4.002 2.498A.5.5 0 0 1 8 12.498z\"\n      fill=\"#253627\"\n    />\n    <path\n      d=\"m5.1 8.716 1.047 5.145a.702.702 0 0 1-1.107-.422l-.814-4.007L.427 7.826A.699.699 0 0 1 .362 6.57l3.603-1.983.38-3.953a.701.701 0 0 1 1.158-.46L8.574 2.85l4.052-.898a.7.7 0 0 1 .786.978l-1.698 3.631-.854-.533 1.388-2.969-3.95.876L5.284 1.31 4.91 5.208 1.388 7.146z\"\n      fill=\"#C77D55\"\n    />\n  </svg>\n);\n\nexport const SparkRun: React.FC<SparkRunProps> = ({\n  size = 'md',\n  mode = 'light',\n  className,\n  'aria-label': ariaLabel,\n  title,\n  ...props\n}) => {\n  const SvgComponent = mode === 'light' ? SparkRunLight : SparkRunDark;\n\n  return (\n    <SvgComponent\n      size={sizeMap[size]}\n      className={cn('inline-block flex-shrink-0', className)}\n      title={title}\n      role={ariaLabel ? 'img' : 'presentation'}\n      aria-label={ariaLabel}\n      aria-hidden={!ariaLabel}\n      {...props}\n    />\n  );\n};"
    },
    {
      "path": "registry/icons/plugins/bdt/zeppelin/index.tsx",
      "type": "registry:ui",
      "target": "components/jetbrains-ui/icons/plugins/bdt/zeppelin/index.tsx",
      "content": "import React from 'react';\nimport { cn } from '@/lib/utils';\nimport { type IconProps, type SvgProps, sizeMap } from '../../types';\n\nexport type ZeppelinProps = IconProps;\n\nconst ZeppelinLight: React.FC<SvgProps> = ({\n  size,\n  className,\n  title,\n  role,\n  'aria-label': ariaLabel,\n  'aria-hidden': ariaHidden,\n}) => (\n  <svg\n    width={size}\n    height={size}\n    viewBox=\"0 0 16 16\"\n    fill=\"none\"\n    xmlns=\"http://www.w3.org/2000/svg\"\n    className={className}\n    role={role}\n    aria-label={ariaLabel}\n    aria-hidden={ariaHidden}\n  >\n    {title && <title>{title}</title>}\n    <path\n      fillRule=\"evenodd\"\n      clipRule=\"evenodd\"\n      d=\"M11.477 3.019c-1.394-.006-2.94.43-3.772.943-.311.192-.63.407-.95.634 0 0-2.888 2.224-3.786 3.343q-.181.226-.325.482l-.02.037-.026.05-.006.012a3.4 3.4 0 0 0-.303.92v.009l-.005.033c-.049.368-.029.76.122 1.092.183.405.487.707.928.954.426.24 1.205.443 1.205.443l-.013.006c.649.115 1.321.076 1.977.012q.483-.045.966-.107h.013c-.022-.108-.056-.315-.014-.326.441-.117.704-.188 1.047-.307.329-.115.57-.219.836-.366.066-.036.119-.098.189-.128.22-.094.466-.117.703-.153q.285-.045.572-.052c.125-.002.25-.005.373.019a.8.8 0 0 1 .27.093.44.44 0 0 1 .14.13q.027.061.05.125c.696-.261 1.404-.576 1.942-1.087.796-.755 1.428-1.743 1.741-2.794.17-.572.2-1.214.038-1.788-.1-.354-.253-.583-.597-.93-.702-.713-1.725-1.153-2.718-1.267a5 5 0 0 0-.577-.032M6.755 4.596q-.215.152-.428.31zm3.006.672c.452-.001.702.068.702.068s-.743.07-1.156.143c-.327.058-.853.16-1.263.298-.8.271-1.56.65-2.31 1.035-.578.296-1.13.638-1.683.978-.377.233-1.114.726-1.114.726s.628-.811 2.298-1.749c.477-.268.964-.52 1.464-.743.39-.175.787-.341 1.196-.466a7.3 7.3 0 0 1 1.66-.284 5 5 0 0 1 .206-.006m-5.728.774c-.148.001-.275.175-.353.306-.1.167-.144.455-.165.685.32-.274.64-.529.862-.701-.085-.144-.193-.269-.314-.287zm6.456.733s-1.394.53-2.087.806q-1.198.476-2.383.983-.828.354-1.647.731c-.503.23-1.498.71-1.498.71s.848-.695 2.42-1.383c.919-.4 1.537-.752 2.525-1.075.462-.15.917-.32 1.383-.454.425-.122 1.287-.318 1.287-.318m.484 1.415s-.196.233-.632.522c-.219.145-.41.296-.625.429a10 10 0 0 1-.856.475c-.364.177-.742.326-1.118.474-.369.146-.74.288-1.118.41-.466.15-.936.287-1.415.391-.347.076-1.052.167-1.052.167s.87-.294 1.303-.447a56.066 56.066 0 0 0 2.635-.985c.344-.139.69-.273 1.025-.43.257-.12.506-.256.755-.39.37-.2 1.098-.616 1.098-.616m1.013.914s-.011.145-.379.52a3.6 3.6 0 0 1-.576.451c-.645.398-.989.5-.989.5s.637-.417.945-.64q.273-.196.532-.412c.161-.133.467-.419.467-.419m-9.893 1.377c-.216.098-.477.218-.648.31-.318.17-.942.467-.921.563.031.148.738-.137 1.106-.21q.35-.07.7-.146a3 3 0 0 1-.237-.517m8.637.236c-.094 0-.194.006-.316.02-.373.041-.473.075-.772.172-.106.034-.169.09-.252.136-.15.082-.291.181-.447.25-.225.1-.463.165-.698.236-.194.059-.221.07-.587.158-.064.015-.004.119.053.198.868.018 3.493.06 3.528-.087l.194-.804.052-.018a.3.3 0 0 0-.028-.074.34.34 0 0 0-.135-.13c-.094-.047-.206-.04-.31-.046a4 4 0 0 0-.282-.01m.475.217c.104.002.188.018.188.07-.002.11-.24.105-.35.116-.705.07-.953.057-1.43.06-.091 0-.274-.01-.274-.01s.458-.109.866-.158c.236-.028.467-.058.694-.065.078-.003.202-.015.306-.013m-.54.442q.127-.002.253.013c.066.01.14.013.192.055.023.02.05.06.04.08-.018.04-.09.042-.24.052-.181.012-.358.027-.537.032-.444.013-1.333-.002-1.333-.002s.277-.074.418-.1q.473-.085.952-.117.127-.009.254-.013\"\n      fill=\"#4682FA\"\n    />\n    <path\n      fillRule=\"evenodd\"\n      clipRule=\"evenodd\"\n      d=\"M11.477 3.019c-1.394-.006-2.94.43-3.772.943-.311.192-.63.407-.95.634 0 0-2.888 2.224-3.786 3.343q-.181.226-.325.482l-.02.037-.026.05-.006.012a3.4 3.4 0 0 0-.303.92v.009l-.005.033c-.049.368-.029.76.122 1.092.183.405.487.707.928.954.426.24 1.205.443 1.205.443l-.013.006c.649.115 1.321.076 1.977.012q.483-.045.966-.107h.013c-.022-.108-.056-.315-.014-.326.441-.117.704-.188 1.047-.307.329-.115.57-.219.836-.366.066-.036.119-.098.189-.128.22-.094.466-.117.703-.153q.285-.045.572-.052c.125-.002.25-.005.373.019a.8.8 0 0 1 .27.093.44.44 0 0 1 .14.13q.027.061.05.125c.696-.261 1.404-.576 1.942-1.087.796-.755 1.428-1.743 1.741-2.794.17-.572.2-1.214.038-1.788-.1-.354-.253-.583-.597-.93-.702-.713-1.725-1.153-2.718-1.267a5 5 0 0 0-.577-.032M6.755 4.596q-.215.152-.428.31zm3.006.672c.452-.001.702.068.702.068s-.743.07-1.156.143c-.327.058-.853.16-1.263.298-.8.271-1.56.65-2.31 1.035-.578.296-1.13.638-1.683.978-.377.233-1.114.726-1.114.726s.628-.811 2.298-1.749c.477-.268.964-.52 1.464-.743.39-.175.787-.341 1.196-.466a7.3 7.3 0 0 1 1.66-.284 5 5 0 0 1 .206-.006m-5.728.774c-.148.001-.275.175-.353.306-.1.167-.144.455-.165.685.32-.274.64-.529.862-.701-.085-.144-.193-.269-.314-.287zm6.456.733s-1.394.53-2.087.806q-1.198.476-2.383.983-.828.354-1.647.731c-.503.23-1.498.71-1.498.71s.848-.695 2.42-1.383c.919-.4 1.537-.752 2.525-1.075.462-.15.917-.32 1.383-.454.425-.122 1.287-.318 1.287-.318m.484 1.415s-.196.233-.632.522c-.219.145-.41.296-.625.429a10 10 0 0 1-.856.475c-.364.177-.742.326-1.118.474-.369.146-.74.288-1.118.41-.466.15-.936.287-1.415.391-.347.076-1.052.167-1.052.167s.87-.294 1.303-.447a56.066 56.066 0 0 0 2.635-.985c.344-.139.69-.273 1.025-.43.257-.12.506-.256.755-.39.37-.2 1.098-.616 1.098-.616m1.013.914s-.011.145-.379.52a3.6 3.6 0 0 1-.576.451c-.645.398-.989.5-.989.5s.637-.417.945-.64q.273-.196.532-.412c.161-.133.467-.419.467-.419m-9.893 1.377c-.216.098-.477.218-.648.31-.318.17-.942.467-.921.563.031.148.738-.137 1.106-.21q.35-.07.7-.146a3 3 0 0 1-.237-.517m8.637.236c-.094 0-.194.006-.316.02-.373.041-.473.075-.772.172-.106.034-.169.09-.252.136-.15.082-.291.181-.447.25-.225.1-.463.165-.698.236-.194.059-.221.07-.587.158-.064.015-.004.119.053.198.868.018 3.493.06 3.528-.087l.194-.804.052-.018a.3.3 0 0 0-.028-.074.34.34 0 0 0-.135-.13c-.094-.047-.206-.04-.31-.046a4 4 0 0 0-.282-.01m.475.217c.104.002.188.018.188.07-.002.11-.24.105-.35.116-.705.07-.953.057-1.43.06-.091 0-.274-.01-.274-.01s.458-.109.866-.158c.236-.028.467-.058.694-.065.078-.003.202-.015.306-.013m-.54.442q.127-.002.253.013c.066.01.14.013.192.055.023.02.05.06.04.08-.018.04-.09.042-.24.052-.181.012-.358.027-.537.032-.444.013-1.333-.002-1.333-.002s.277-.074.418-.1q.473-.085.952-.117.127-.009.254-.013\"\n      fill=\"#4682FA\"\n    />\n  </svg>\n);\n\nconst ZeppelinDark: React.FC<SvgProps> = ({\n  size,\n  className,\n  title,\n  role,\n  'aria-label': ariaLabel,\n  'aria-hidden': ariaHidden,\n}) => (\n  <svg\n    width={size}\n    height={size}\n    viewBox=\"0 0 16 16\"\n    fill=\"none\"\n    xmlns=\"http://www.w3.org/2000/svg\"\n    className={className}\n    role={role}\n    aria-label={ariaLabel}\n    aria-hidden={ariaHidden}\n  >\n    {title && <title>{title}</title>}\n    <path\n      fillRule=\"evenodd\"\n      clipRule=\"evenodd\"\n      d=\"M11.477 3.019c-1.394-.006-2.94.43-3.772.943-.311.192-.63.407-.95.634 0 0-2.888 2.224-3.786 3.343q-.181.226-.325.482l-.02.037-.026.05-.006.012a3.4 3.4 0 0 0-.303.92v.009l-.005.033c-.049.368-.029.76.122 1.092.183.405.487.707.928.954.426.24 1.205.443 1.205.443l-.013.006c.649.115 1.321.076 1.977.012q.483-.045.966-.107h.013c-.022-.108-.056-.315-.014-.326.441-.117.704-.188 1.047-.307.329-.115.57-.219.836-.366.066-.036.119-.098.189-.128.22-.094.466-.117.703-.153q.285-.045.572-.052c.125-.002.25-.005.373.019a.8.8 0 0 1 .27.093.44.44 0 0 1 .14.13q.027.061.05.125c.696-.261 1.404-.576 1.942-1.087.796-.755 1.428-1.743 1.741-2.794.17-.572.2-1.214.038-1.788-.1-.354-.253-.583-.597-.93-.702-.713-1.725-1.153-2.718-1.267a5 5 0 0 0-.577-.032M6.755 4.596q-.215.152-.428.31zm3.006.672c.452-.001.702.068.702.068s-.743.07-1.156.143c-.327.058-.853.16-1.263.298-.8.271-1.56.65-2.31 1.035-.578.296-1.13.638-1.683.978-.377.233-1.114.726-1.114.726s.628-.811 2.298-1.749c.477-.268.964-.52 1.464-.743.39-.175.787-.341 1.196-.466a7.3 7.3 0 0 1 1.66-.284 5 5 0 0 1 .206-.006m-5.728.774c-.148.001-.275.175-.353.306-.1.167-.144.455-.165.685.32-.274.64-.529.862-.701-.085-.144-.193-.269-.314-.287zm6.456.733s-1.394.53-2.087.806q-1.198.476-2.383.983-.828.354-1.647.731c-.503.23-1.498.71-1.498.71s.848-.695 2.42-1.383c.919-.4 1.537-.752 2.525-1.075.462-.15.917-.32 1.383-.454.425-.122 1.287-.318 1.287-.318m.484 1.415s-.196.233-.632.522c-.219.145-.41.296-.625.429a10 10 0 0 1-.856.475c-.364.177-.742.326-1.118.474-.369.146-.74.288-1.118.41-.466.15-.936.287-1.415.391-.347.076-1.052.167-1.052.167s.87-.294 1.303-.447a56.066 56.066 0 0 0 2.635-.985c.344-.139.69-.273 1.025-.43.257-.12.506-.256.755-.39.37-.2 1.098-.616 1.098-.616m1.013.914s-.011.145-.379.52a3.6 3.6 0 0 1-.576.451c-.645.398-.989.5-.989.5s.637-.417.945-.64q.273-.196.532-.412c.161-.133.467-.419.467-.419m-9.893 1.377c-.216.098-.477.218-.648.31-.318.17-.942.467-.921.563.031.148.738-.137 1.106-.21q.35-.07.7-.146a3 3 0 0 1-.237-.517m8.637.236c-.094 0-.194.006-.316.02-.373.041-.473.075-.772.172-.106.034-.169.09-.252.136-.15.082-.291.181-.447.25-.225.1-.463.165-.698.236-.194.059-.221.07-.587.158-.064.015-.004.119.053.198.868.018 3.493.06 3.528-.087l.194-.804.052-.018a.3.3 0 0 0-.028-.074.34.34 0 0 0-.135-.13c-.094-.047-.206-.04-.31-.046a4 4 0 0 0-.282-.01m.475.217c.104.002.188.018.188.07-.002.11-.24.105-.35.116-.705.07-.953.057-1.43.06-.091 0-.274-.01-.274-.01s.458-.109.866-.158c.236-.028.467-.058.694-.065.078-.003.202-.015.306-.013m-.54.442q.127-.002.253.013c.066.01.14.013.192.055.023.02.05.06.04.08-.018.04-.09.042-.24.052-.181.012-.358.027-.537.032-.444.013-1.333-.002-1.333-.002s.277-.074.418-.1q.473-.085.952-.117.127-.009.254-.013\"\n      fill=\"#548AF7\"\n    />\n    <path\n      fillRule=\"evenodd\"\n      clipRule=\"evenodd\"\n      d=\"M11.477 3.019c-1.394-.006-2.94.43-3.772.943-.311.192-.63.407-.95.634 0 0-2.888 2.224-3.786 3.343q-.181.226-.325.482l-.02.037-.026.05-.006.012a3.4 3.4 0 0 0-.303.92v.009l-.005.033c-.049.368-.029.76.122 1.092.183.405.487.707.928.954.426.24 1.205.443 1.205.443l-.013.006c.649.115 1.321.076 1.977.012q.483-.045.966-.107h.013c-.022-.108-.056-.315-.014-.326.441-.117.704-.188 1.047-.307.329-.115.57-.219.836-.366.066-.036.119-.098.189-.128.22-.094.466-.117.703-.153q.285-.045.572-.052c.125-.002.25-.005.373.019a.8.8 0 0 1 .27.093.44.44 0 0 1 .14.13q.027.061.05.125c.696-.261 1.404-.576 1.942-1.087.796-.755 1.428-1.743 1.741-2.794.17-.572.2-1.214.038-1.788-.1-.354-.253-.583-.597-.93-.702-.713-1.725-1.153-2.718-1.267a5 5 0 0 0-.577-.032M6.755 4.596q-.215.152-.428.31zm3.006.672c.452-.001.702.068.702.068s-.743.07-1.156.143c-.327.058-.853.16-1.263.298-.8.271-1.56.65-2.31 1.035-.578.296-1.13.638-1.683.978-.377.233-1.114.726-1.114.726s.628-.811 2.298-1.749c.477-.268.964-.52 1.464-.743.39-.175.787-.341 1.196-.466a7.3 7.3 0 0 1 1.66-.284 5 5 0 0 1 .206-.006m-5.728.774c-.148.001-.275.175-.353.306-.1.167-.144.455-.165.685.32-.274.64-.529.862-.701-.085-.144-.193-.269-.314-.287zm6.456.733s-1.394.53-2.087.806q-1.198.476-2.383.983-.828.354-1.647.731c-.503.23-1.498.71-1.498.71s.848-.695 2.42-1.383c.919-.4 1.537-.752 2.525-1.075.462-.15.917-.32 1.383-.454.425-.122 1.287-.318 1.287-.318m.484 1.415s-.196.233-.632.522c-.219.145-.41.296-.625.429a10 10 0 0 1-.856.475c-.364.177-.742.326-1.118.474-.369.146-.74.288-1.118.41-.466.15-.936.287-1.415.391-.347.076-1.052.167-1.052.167s.87-.294 1.303-.447a56.066 56.066 0 0 0 2.635-.985c.344-.139.69-.273 1.025-.43.257-.12.506-.256.755-.39.37-.2 1.098-.616 1.098-.616m1.013.914s-.011.145-.379.52a3.6 3.6 0 0 1-.576.451c-.645.398-.989.5-.989.5s.637-.417.945-.64q.273-.196.532-.412c.161-.133.467-.419.467-.419m-9.893 1.377c-.216.098-.477.218-.648.31-.318.17-.942.467-.921.563.031.148.738-.137 1.106-.21q.35-.07.7-.146a3 3 0 0 1-.237-.517m8.637.236c-.094 0-.194.006-.316.02-.373.041-.473.075-.772.172-.106.034-.169.09-.252.136-.15.082-.291.181-.447.25-.225.1-.463.165-.698.236-.194.059-.221.07-.587.158-.064.015-.004.119.053.198.868.018 3.493.06 3.528-.087l.194-.804.052-.018a.3.3 0 0 0-.028-.074.34.34 0 0 0-.135-.13c-.094-.047-.206-.04-.31-.046a4 4 0 0 0-.282-.01m.475.217c.104.002.188.018.188.07-.002.11-.24.105-.35.116-.705.07-.953.057-1.43.06-.091 0-.274-.01-.274-.01s.458-.109.866-.158c.236-.028.467-.058.694-.065.078-.003.202-.015.306-.013m-.54.442q.127-.002.253.013c.066.01.14.013.192.055.023.02.05.06.04.08-.018.04-.09.042-.24.052-.181.012-.358.027-.537.032-.444.013-1.333-.002-1.333-.002s.277-.074.418-.1q.473-.085.952-.117.127-.009.254-.013\"\n      fill=\"#548AF7\"\n    />\n  </svg>\n);\n\nexport const Zeppelin: React.FC<ZeppelinProps> = ({\n  size = 'md',\n  mode = 'light',\n  className,\n  'aria-label': ariaLabel,\n  title,\n  ...props\n}) => {\n  const SvgComponent = mode === 'light' ? ZeppelinLight : ZeppelinDark;\n\n  return (\n    <SvgComponent\n      size={sizeMap[size]}\n      className={cn('inline-block flex-shrink-0', className)}\n      title={title}\n      role={ariaLabel ? 'img' : 'presentation'}\n      aria-label={ariaLabel}\n      aria-hidden={!ariaLabel}\n      {...props}\n    />\n  );\n};"
    }
  ],
  "meta": {
    "keywords": [
      "icons",
      "plugins",
      "bdt",
      "jetbrains",
      "icon-pack"
    ]
  }
}