{
  "name": "icons-file-types-ui-form",
  "type": "registry:ui",
  "title": "Ui Form",
  "description": "Ui Form icon from File Types category.",
  "registryDependencies": [
    "utils",
    "@jetbrains-ui/icons-file-types-types"
  ],
  "files": [
    {
      "path": "registry/icons/file-types/ui-form/index.tsx",
      "type": "registry:ui",
      "target": "components/jetbrains-ui/icons/file-types/ui-form/index.tsx",
      "content": "import type { FC } from 'react';\nimport { cn } from '@/lib/utils';\nimport { type IconProps, type SvgProps, sizeMap } from '../types';\n\nexport type UiFormProps = IconProps;\n\nconst UiFormLight: FC<SvgProps> = ({\n  size,\n  className,\n  title,\n  role,\n  'aria-label': ariaLabel,\n  'aria-hidden': ariaHidden,\n}) => (\n  <svg\n    width={size}\n    height={size}\n    viewBox=\"0 0 16 16\"\n    fill=\"none\"\n    xmlns=\"http://www.w3.org/2000/svg\"\n    className={className}\n    role={role}\n    aria-label={ariaLabel}\n    aria-hidden={ariaHidden}\n  >\n    {title ? <title>{title}</title> : null}\n    <path\n      fillRule=\"evenodd\"\n      clipRule=\"evenodd\"\n      d=\"M1 4a2 2 0 0 1 2-2h10a2 2 0 0 1 2 2v8a2 2 0 0 1-2 2H3a2 2 0 0 1-2-2zm2-1h10a1 1 0 0 1 1 1v1H2V4a1 1 0 0 1 1-1M2 6v6a1 1 0 0 0 1 1h10a1 1 0 0 0 1-1V6z\"\n      fill=\"#6C707E\"\n    />\n  </svg>\n);\n\nconst UiFormDark: FC<SvgProps> = ({\n  size,\n  className,\n  title,\n  role,\n  'aria-label': ariaLabel,\n  'aria-hidden': ariaHidden,\n}) => (\n  <svg\n    width={size}\n    height={size}\n    viewBox=\"0 0 16 16\"\n    fill=\"none\"\n    xmlns=\"http://www.w3.org/2000/svg\"\n    className={className}\n    role={role}\n    aria-label={ariaLabel}\n    aria-hidden={ariaHidden}\n  >\n    {title ? <title>{title}</title> : null}\n    <g clipPath=\"url(#a)\">\n      <path\n        fillRule=\"evenodd\"\n        clipRule=\"evenodd\"\n        d=\"M1 4a2 2 0 0 1 2-2h10a2 2 0 0 1 2 2v8a2 2 0 0 1-2 2H3a2 2 0 0 1-2-2zm2-1h10a1 1 0 0 1 1 1v1H2V4a1 1 0 0 1 1-1M2 6v6a1 1 0 0 0 1 1h10a1 1 0 0 0 1-1V6z\"\n        fill=\"#CED0D6\"\n      />\n    </g>\n    <defs>\n      <clipPath id=\"a\">\n        <path fill=\"#fff\" d=\"M0 0H16V16H0z\" />\n      </clipPath>\n    </defs>\n  </svg>\n);\n\nexport const UiForm: FC<UiFormProps> = ({\n  size = 'md',\n  mode = 'light',\n  className,\n  'aria-label': ariaLabel,\n  title,\n  ...props\n}) => {\n  const SvgComponent = mode === 'light' ? UiFormLight : UiFormDark;\n\n  return (\n    <SvgComponent\n      size={sizeMap[size]}\n      className={cn('inline-block flex-shrink-0', className)}\n      title={title}\n      role={ariaLabel ? 'img' : 'presentation'}\n      aria-label={ariaLabel}\n      aria-hidden={!ariaLabel}\n      {...props}\n    />\n  );\n};"
    }
  ],
  "meta": {
    "keywords": [
      "ui-form",
      "icon",
      "file-types",
      "jetbrains"
    ]
  }
}